{"eleccionId":"nacionales-2014","departamento":"montevideo","nivel":"zona","escrutinio":"definitivo","tipo":"nacionales","zonas":[{"geoId":"Ciudad Vieja","ganadorOpcionId":"unica-asamblea-popular-326","validos":296,"porOpcion":[{"opcionId":"unica-asamblea-popular-326","votos":119},{"opcionId":"unica-asamblea-popular-960","votos":51},{"opcionId":"unica-asamblea-popular-1969","votos":44},{"opcionId":"unica-asamblea-popular-3060","votos":36},{"opcionId":"unica-asamblea-popular-13013","votos":20},{"opcionId":"unica-asamblea-popular-vl","votos":18},{"opcionId":"unica-asamblea-popular-101114","votos":8}],"noPartidarios":{"enBlanco":0,"anulados":0,"observados":0}},{"geoId":"Barrio Sur","ganadorOpcionId":"unica-asamblea-popular-326","validos":136,"porOpcion":[{"opcionId":"unica-asamblea-popular-326","votos":69},{"opcionId":"unica-asamblea-popular-1969","votos":20},{"opcionId":"unica-asamblea-popular-960","votos":20},{"opcionId":"unica-asamblea-popular-3060","votos":11},{"opcionId":"unica-asamblea-popular-vl","votos":9},{"opcionId":"unica-asamblea-popular-13013","votos":4},{"opcionId":"unica-asamblea-popular-101114","votos":3}],"noPartidarios":{"enBlanco":0,"anulados":0,"observados":0}},{"geoId":"Centro","ganadorOpcionId":"unica-asamblea-popular-326","validos":254,"porOpcion":[{"opcionId":"unica-asamblea-popular-326","votos":136},{"opcionId":"unica-asamblea-popular-960","votos":36},{"opcionId":"unica-asamblea-popular-1969","votos":34},{"opcionId":"unica-asamblea-popular-3060","votos":24},{"opcionId":"unica-asamblea-popular-vl","votos":11},{"opcionId":"unica-asamblea-popular-13013","votos":9},{"opcionId":"unica-asamblea-popular-101114","votos":4}],"noPartidarios":{"enBlanco":0,"anulados":0,"observados":0}},{"geoId":"Cordón","ganadorOpcionId":"unica-asamblea-popular-326","validos":643,"porOpcion":[{"opcionId":"unica-asamblea-popular-326","votos":280},{"opcionId":"unica-asamblea-popular-960","votos":117},{"opcionId":"unica-asamblea-popular-1969","votos":109},{"opcionId":"unica-asamblea-popular-3060","votos":63},{"opcionId":"unica-asamblea-popular-13013","votos":32},{"opcionId":"unica-asamblea-popular-vl","votos":29},{"opcionId":"unica-asamblea-popular-101114","votos":13}],"noPartidarios":{"enBlanco":0,"anulados":0,"observados":0}},{"geoId":"Manga, Toledo Chico","ganadorOpcionId":"unica-asamblea-popular-326","validos":165,"porOpcion":[{"opcionId":"unica-asamblea-popular-326","votos":69},{"opcionId":"unica-asamblea-popular-1969","votos":29},{"opcionId":"unica-asamblea-popular-960","votos":24},{"opcionId":"unica-asamblea-popular-3060","votos":20},{"opcionId":"unica-asamblea-popular-13013","votos":14},{"opcionId":"unica-asamblea-popular-vl","votos":6},{"opcionId":"unica-asamblea-popular-101114","votos":3}],"noPartidarios":{"enBlanco":0,"anulados":0,"observados":0}},{"geoId":"Palermo","ganadorOpcionId":"unica-asamblea-popular-326","validos":171,"porOpcion":[{"opcionId":"unica-asamblea-popular-326","votos":77},{"opcionId":"unica-asamblea-popular-1969","votos":30},{"opcionId":"unica-asamblea-popular-960","votos":27},{"opcionId":"unica-asamblea-popular-3060","votos":18},{"opcionId":"unica-asamblea-popular-13013","votos":10},{"opcionId":"unica-asamblea-popular-101114","votos":5},{"opcionId":"unica-asamblea-popular-vl","votos":4}],"noPartidarios":{"enBlanco":0,"anulados":0,"observados":0}},{"geoId":"Parque Rodó","ganadorOpcionId":"unica-asamblea-popular-326","validos":171,"porOpcion":[{"opcionId":"unica-asamblea-popular-326","votos":89},{"opcionId":"unica-asamblea-popular-1969","votos":28},{"opcionId":"unica-asamblea-popular-3060","votos":22},{"opcionId":"unica-asamblea-popular-960","votos":17},{"opcionId":"unica-asamblea-popular-vl","votos":7},{"opcionId":"unica-asamblea-popular-13013","votos":6},{"opcionId":"unica-asamblea-popular-101114","votos":2}],"noPartidarios":{"enBlanco":0,"anulados":0,"observados":0}},{"geoId":"Tres Cruces","ganadorOpcionId":"unica-asamblea-popular-326","validos":154,"porOpcion":[{"opcionId":"unica-asamblea-popular-326","votos":79},{"opcionId":"unica-asamblea-popular-960","votos":23},{"opcionId":"unica-asamblea-popular-1969","votos":23},{"opcionId":"unica-asamblea-popular-3060","votos":17},{"opcionId":"unica-asamblea-popular-13013","votos":6},{"opcionId":"unica-asamblea-popular-vl","votos":5},{"opcionId":"unica-asamblea-popular-101114","votos":1}],"noPartidarios":{"enBlanco":0,"anulados":0,"observados":0}},{"geoId":"Parque Batlle, Villa Dolores","ganadorOpcionId":"unica-asamblea-popular-326","validos":373,"porOpcion":[{"opcionId":"unica-asamblea-popular-326","votos":173},{"opcionId":"unica-asamblea-popular-1969","votos":58},{"opcionId":"unica-asamblea-popular-960","votos":55},{"opcionId":"unica-asamblea-popular-3060","votos":40},{"opcionId":"unica-asamblea-popular-13013","votos":21},{"opcionId":"unica-asamblea-popular-vl","votos":18},{"opcionId":"unica-asamblea-popular-101114","votos":8}],"noPartidarios":{"enBlanco":0,"anulados":0,"observados":0}},{"geoId":"La Blanqueada","ganadorOpcionId":"unica-asamblea-popular-326","validos":334,"porOpcion":[{"opcionId":"unica-asamblea-popular-326","votos":158},{"opcionId":"unica-asamblea-popular-960","votos":66},{"opcionId":"unica-asamblea-popular-1969","votos":53},{"opcionId":"unica-asamblea-popular-3060","votos":26},{"opcionId":"unica-asamblea-popular-13013","votos":11},{"opcionId":"unica-asamblea-popular-101114","votos":11},{"opcionId":"unica-asamblea-popular-vl","votos":9}],"noPartidarios":{"enBlanco":0,"anulados":0,"observados":0}},{"geoId":"Unión","ganadorOpcionId":"unica-asamblea-popular-326","validos":401,"porOpcion":[{"opcionId":"unica-asamblea-popular-326","votos":201},{"opcionId":"unica-asamblea-popular-960","votos":69},{"opcionId":"unica-asamblea-popular-1969","votos":53},{"opcionId":"unica-asamblea-popular-3060","votos":46},{"opcionId":"unica-asamblea-popular-13013","votos":12},{"opcionId":"unica-asamblea-popular-vl","votos":11},{"opcionId":"unica-asamblea-popular-101114","votos":9}],"noPartidarios":{"enBlanco":0,"anulados":0,"observados":0}},{"geoId":"Larrañaga","ganadorOpcionId":"unica-asamblea-popular-326","validos":159,"porOpcion":[{"opcionId":"unica-asamblea-popular-326","votos":56},{"opcionId":"unica-asamblea-popular-1969","votos":34},{"opcionId":"unica-asamblea-popular-960","votos":29},{"opcionId":"unica-asamblea-popular-3060","votos":18},{"opcionId":"unica-asamblea-popular-vl","votos":12},{"opcionId":"unica-asamblea-popular-13013","votos":8},{"opcionId":"unica-asamblea-popular-101114","votos":2}],"noPartidarios":{"enBlanco":0,"anulados":0,"observados":0}},{"geoId":"Buceo","ganadorOpcionId":"unica-asamblea-popular-326","validos":519,"porOpcion":[{"opcionId":"unica-asamblea-popular-326","votos":242},{"opcionId":"unica-asamblea-popular-1969","votos":93},{"opcionId":"unica-asamblea-popular-960","votos":69},{"opcionId":"unica-asamblea-popular-3060","votos":62},{"opcionId":"unica-asamblea-popular-13013","votos":27},{"opcionId":"unica-asamblea-popular-vl","votos":18},{"opcionId":"unica-asamblea-popular-101114","votos":8}],"noPartidarios":{"enBlanco":0,"anulados":0,"observados":0}},{"geoId":"Pocitos","ganadorOpcionId":"unica-asamblea-popular-326","validos":403,"porOpcion":[{"opcionId":"unica-asamblea-popular-326","votos":197},{"opcionId":"unica-asamblea-popular-1969","votos":73},{"opcionId":"unica-asamblea-popular-960","votos":58},{"opcionId":"unica-asamblea-popular-3060","votos":31},{"opcionId":"unica-asamblea-popular-13013","votos":27},{"opcionId":"unica-asamblea-popular-vl","votos":11},{"opcionId":"unica-asamblea-popular-101114","votos":6}],"noPartidarios":{"enBlanco":0,"anulados":0,"observados":0}},{"geoId":"Punta Carretas","ganadorOpcionId":"unica-asamblea-popular-326","validos":200,"porOpcion":[{"opcionId":"unica-asamblea-popular-326","votos":93},{"opcionId":"unica-asamblea-popular-1969","votos":41},{"opcionId":"unica-asamblea-popular-960","votos":30},{"opcionId":"unica-asamblea-popular-3060","votos":14},{"opcionId":"unica-asamblea-popular-13013","votos":12},{"opcionId":"unica-asamblea-popular-vl","votos":7},{"opcionId":"unica-asamblea-popular-101114","votos":3}],"noPartidarios":{"enBlanco":0,"anulados":0,"observados":0}},{"geoId":"Mercado Modelo, Bolívar","ganadorOpcionId":"unica-asamblea-popular-326","validos":324,"porOpcion":[{"opcionId":"unica-asamblea-popular-326","votos":147},{"opcionId":"unica-asamblea-popular-1969","votos":50},{"opcionId":"unica-asamblea-popular-960","votos":44},{"opcionId":"unica-asamblea-popular-13013","votos":32},{"opcionId":"unica-asamblea-popular-3060","votos":26},{"opcionId":"unica-asamblea-popular-vl","votos":18},{"opcionId":"unica-asamblea-popular-101114","votos":7}],"noPartidarios":{"enBlanco":0,"anulados":0,"observados":0}},{"geoId":"Peñarol, Lavalleja","ganadorOpcionId":"unica-asamblea-popular-326","validos":708,"porOpcion":[{"opcionId":"unica-asamblea-popular-326","votos":337},{"opcionId":"unica-asamblea-popular-960","votos":109},{"opcionId":"unica-asamblea-popular-1969","votos":87},{"opcionId":"unica-asamblea-popular-3060","votos":83},{"opcionId":"unica-asamblea-popular-13013","votos":51},{"opcionId":"unica-asamblea-popular-vl","votos":27},{"opcionId":"unica-asamblea-popular-101114","votos":14}],"noPartidarios":{"enBlanco":0,"anulados":0,"observados":0}},{"geoId":"Castro, P. Castellanos","ganadorOpcionId":"unica-asamblea-popular-326","validos":212,"porOpcion":[{"opcionId":"unica-asamblea-popular-326","votos":99},{"opcionId":"unica-asamblea-popular-1969","votos":36},{"opcionId":"unica-asamblea-popular-960","votos":33},{"opcionId":"unica-asamblea-popular-3060","votos":23},{"opcionId":"unica-asamblea-popular-13013","votos":15},{"opcionId":"unica-asamblea-popular-vl","votos":4},{"opcionId":"unica-asamblea-popular-101114","votos":2}],"noPartidarios":{"enBlanco":0,"anulados":0,"observados":0}},{"geoId":"Villa Española","ganadorOpcionId":"unica-asamblea-popular-326","validos":302,"porOpcion":[{"opcionId":"unica-asamblea-popular-326","votos":118},{"opcionId":"unica-asamblea-popular-960","votos":49},{"opcionId":"unica-asamblea-popular-1969","votos":44},{"opcionId":"unica-asamblea-popular-13013","votos":35},{"opcionId":"unica-asamblea-popular-3060","votos":34},{"opcionId":"unica-asamblea-popular-vl","votos":12},{"opcionId":"unica-asamblea-popular-101114","votos":10}],"noPartidarios":{"enBlanco":0,"anulados":0,"observados":0}},{"geoId":"Malvín","ganadorOpcionId":"unica-asamblea-popular-326","validos":290,"porOpcion":[{"opcionId":"unica-asamblea-popular-326","votos":135},{"opcionId":"unica-asamblea-popular-1969","votos":51},{"opcionId":"unica-asamblea-popular-960","votos":38},{"opcionId":"unica-asamblea-popular-3060","votos":38},{"opcionId":"unica-asamblea-popular-13013","votos":13},{"opcionId":"unica-asamblea-popular-vl","votos":8},{"opcionId":"unica-asamblea-popular-101114","votos":7}],"noPartidarios":{"enBlanco":0,"anulados":0,"observados":0}},{"geoId":"Malvín Norte","ganadorOpcionId":"unica-asamblea-popular-326","validos":237,"porOpcion":[{"opcionId":"unica-asamblea-popular-326","votos":113},{"opcionId":"unica-asamblea-popular-960","votos":39},{"opcionId":"unica-asamblea-popular-1969","votos":34},{"opcionId":"unica-asamblea-popular-13013","votos":24},{"opcionId":"unica-asamblea-popular-3060","votos":20},{"opcionId":"unica-asamblea-popular-vl","votos":4},{"opcionId":"unica-asamblea-popular-101114","votos":3}],"noPartidarios":{"enBlanco":0,"anulados":0,"observados":0}},{"geoId":"Las Canteras","ganadorOpcionId":"unica-asamblea-popular-326","validos":255,"porOpcion":[{"opcionId":"unica-asamblea-popular-326","votos":135},{"opcionId":"unica-asamblea-popular-960","votos":41},{"opcionId":"unica-asamblea-popular-1969","votos":39},{"opcionId":"unica-asamblea-popular-3060","votos":22},{"opcionId":"unica-asamblea-popular-vl","votos":7},{"opcionId":"unica-asamblea-popular-13013","votos":7},{"opcionId":"unica-asamblea-popular-101114","votos":4}],"noPartidarios":{"enBlanco":0,"anulados":0,"observados":0}},{"geoId":"Maroñas, Parque Guaraní","ganadorOpcionId":"unica-asamblea-popular-326","validos":129,"porOpcion":[{"opcionId":"unica-asamblea-popular-326","votos":54},{"opcionId":"unica-asamblea-popular-1969","votos":26},{"opcionId":"unica-asamblea-popular-3060","votos":20},{"opcionId":"unica-asamblea-popular-960","votos":18},{"opcionId":"unica-asamblea-popular-vl","votos":6},{"opcionId":"unica-asamblea-popular-13013","votos":3},{"opcionId":"unica-asamblea-popular-101114","votos":2}],"noPartidarios":{"enBlanco":0,"anulados":0,"observados":0}},{"geoId":"Punta Gorda","ganadorOpcionId":"unica-asamblea-popular-326","validos":214,"porOpcion":[{"opcionId":"unica-asamblea-popular-326","votos":110},{"opcionId":"unica-asamblea-popular-1969","votos":31},{"opcionId":"unica-asamblea-popular-960","votos":31},{"opcionId":"unica-asamblea-popular-13013","votos":17},{"opcionId":"unica-asamblea-popular-3060","votos":13},{"opcionId":"unica-asamblea-popular-vl","votos":7},{"opcionId":"unica-asamblea-popular-101114","votos":5}],"noPartidarios":{"enBlanco":0,"anulados":0,"observados":0}},{"geoId":"Carrasco","ganadorOpcionId":"unica-asamblea-popular-326","validos":97,"porOpcion":[{"opcionId":"unica-asamblea-popular-326","votos":35},{"opcionId":"unica-asamblea-popular-1969","votos":20},{"opcionId":"unica-asamblea-popular-960","votos":15},{"opcionId":"unica-asamblea-popular-3060","votos":14},{"opcionId":"unica-asamblea-popular-vl","votos":5},{"opcionId":"unica-asamblea-popular-13013","votos":5},{"opcionId":"unica-asamblea-popular-101114","votos":3}],"noPartidarios":{"enBlanco":0,"anulados":0,"observados":0}},{"geoId":"Carrasco Norte","ganadorOpcionId":"unica-asamblea-popular-326","validos":87,"porOpcion":[{"opcionId":"unica-asamblea-popular-326","votos":30},{"opcionId":"unica-asamblea-popular-1969","votos":25},{"opcionId":"unica-asamblea-popular-960","votos":16},{"opcionId":"unica-asamblea-popular-3060","votos":6},{"opcionId":"unica-asamblea-popular-13013","votos":5},{"opcionId":"unica-asamblea-popular-vl","votos":4},{"opcionId":"unica-asamblea-popular-101114","votos":1}],"noPartidarios":{"enBlanco":0,"anulados":0,"observados":0}},{"geoId":"Ituzaingó","ganadorOpcionId":"unica-asamblea-popular-326","validos":269,"porOpcion":[{"opcionId":"unica-asamblea-popular-326","votos":130},{"opcionId":"unica-asamblea-popular-960","votos":65},{"opcionId":"unica-asamblea-popular-3060","votos":25},{"opcionId":"unica-asamblea-popular-1969","votos":24},{"opcionId":"unica-asamblea-popular-13013","votos":16},{"opcionId":"unica-asamblea-popular-vl","votos":6},{"opcionId":"unica-asamblea-popular-101114","votos":3}],"noPartidarios":{"enBlanco":0,"anulados":0,"observados":0}},{"geoId":"Jardines del Hipódromo","ganadorOpcionId":"unica-asamblea-popular-326","validos":319,"porOpcion":[{"opcionId":"unica-asamblea-popular-326","votos":114},{"opcionId":"unica-asamblea-popular-960","votos":63},{"opcionId":"unica-asamblea-popular-13013","votos":58},{"opcionId":"unica-asamblea-popular-1969","votos":39},{"opcionId":"unica-asamblea-popular-3060","votos":31},{"opcionId":"unica-asamblea-popular-101114","votos":7},{"opcionId":"unica-asamblea-popular-vl","votos":7}],"noPartidarios":{"enBlanco":0,"anulados":0,"observados":0}},{"geoId":"Flor de Maroñas","ganadorOpcionId":"unica-asamblea-popular-326","validos":114,"porOpcion":[{"opcionId":"unica-asamblea-popular-326","votos":59},{"opcionId":"unica-asamblea-popular-960","votos":22},{"opcionId":"unica-asamblea-popular-1969","votos":18},{"opcionId":"unica-asamblea-popular-3060","votos":10},{"opcionId":"unica-asamblea-popular-vl","votos":3},{"opcionId":"unica-asamblea-popular-101114","votos":1},{"opcionId":"unica-asamblea-popular-13013","votos":1}],"noPartidarios":{"enBlanco":0,"anulados":0,"observados":0}},{"geoId":"Bañados de Carrasco","ganadorOpcionId":"unica-asamblea-popular-326","validos":273,"porOpcion":[{"opcionId":"unica-asamblea-popular-326","votos":125},{"opcionId":"unica-asamblea-popular-3060","votos":38},{"opcionId":"unica-asamblea-popular-960","votos":35},{"opcionId":"unica-asamblea-popular-1969","votos":33},{"opcionId":"unica-asamblea-popular-13013","votos":27},{"opcionId":"unica-asamblea-popular-vl","votos":10},{"opcionId":"unica-asamblea-popular-101114","votos":5}],"noPartidarios":{"enBlanco":0,"anulados":0,"observados":0}},{"geoId":"Punta Rieles, Bella Italia","ganadorOpcionId":"unica-asamblea-popular-326","validos":124,"porOpcion":[{"opcionId":"unica-asamblea-popular-326","votos":57},{"opcionId":"unica-asamblea-popular-960","votos":22},{"opcionId":"unica-asamblea-popular-1969","votos":18},{"opcionId":"unica-asamblea-popular-13013","votos":10},{"opcionId":"unica-asamblea-popular-3060","votos":10},{"opcionId":"unica-asamblea-popular-vl","votos":7}],"noPartidarios":{"enBlanco":0,"anulados":0,"observados":0}},{"geoId":"Villa García, Manga Rural","ganadorOpcionId":"unica-asamblea-popular-326","validos":78,"porOpcion":[{"opcionId":"unica-asamblea-popular-326","votos":27},{"opcionId":"unica-asamblea-popular-13013","votos":17},{"opcionId":"unica-asamblea-popular-960","votos":16},{"opcionId":"unica-asamblea-popular-1969","votos":7},{"opcionId":"unica-asamblea-popular-3060","votos":5},{"opcionId":"unica-asamblea-popular-101114","votos":3},{"opcionId":"unica-asamblea-popular-vl","votos":3}],"noPartidarios":{"enBlanco":0,"anulados":0,"observados":0}},{"geoId":"Piedras Blancas","ganadorOpcionId":"unica-asamblea-popular-326","validos":162,"porOpcion":[{"opcionId":"unica-asamblea-popular-326","votos":94},{"opcionId":"unica-asamblea-popular-960","votos":24},{"opcionId":"unica-asamblea-popular-3060","votos":17},{"opcionId":"unica-asamblea-popular-1969","votos":15},{"opcionId":"unica-asamblea-popular-13013","votos":7},{"opcionId":"unica-asamblea-popular-vl","votos":3},{"opcionId":"unica-asamblea-popular-101114","votos":2}],"noPartidarios":{"enBlanco":0,"anulados":0,"observados":0}},{"geoId":"Villa Muñoz, Retiro","ganadorOpcionId":"unica-asamblea-popular-326","validos":165,"porOpcion":[{"opcionId":"unica-asamblea-popular-326","votos":64},{"opcionId":"unica-asamblea-popular-960","votos":33},{"opcionId":"unica-asamblea-popular-1969","votos":32},{"opcionId":"unica-asamblea-popular-3060","votos":15},{"opcionId":"unica-asamblea-popular-vl","votos":9},{"opcionId":"unica-asamblea-popular-13013","votos":7},{"opcionId":"unica-asamblea-popular-101114","votos":5}],"noPartidarios":{"enBlanco":0,"anulados":0,"observados":0}},{"geoId":"Aguada","ganadorOpcionId":"unica-asamblea-popular-326","validos":305,"porOpcion":[{"opcionId":"unica-asamblea-popular-326","votos":152},{"opcionId":"unica-asamblea-popular-960","votos":58},{"opcionId":"unica-asamblea-popular-1969","votos":32},{"opcionId":"unica-asamblea-popular-3060","votos":31},{"opcionId":"unica-asamblea-popular-13013","votos":12},{"opcionId":"unica-asamblea-popular-101114","votos":10},{"opcionId":"unica-asamblea-popular-vl","votos":10}],"noPartidarios":{"enBlanco":0,"anulados":0,"observados":0}},{"geoId":"La Comercial","ganadorOpcionId":"unica-asamblea-popular-326","validos":55,"porOpcion":[{"opcionId":"unica-asamblea-popular-326","votos":22},{"opcionId":"unica-asamblea-popular-960","votos":11},{"opcionId":"unica-asamblea-popular-13013","votos":6},{"opcionId":"unica-asamblea-popular-1969","votos":5},{"opcionId":"unica-asamblea-popular-3060","votos":5},{"opcionId":"unica-asamblea-popular-101114","votos":3},{"opcionId":"unica-asamblea-popular-vl","votos":3}],"noPartidarios":{"enBlanco":0,"anulados":0,"observados":0}},{"geoId":"Brazo Oriental","ganadorOpcionId":"unica-asamblea-popular-326","validos":134,"porOpcion":[{"opcionId":"unica-asamblea-popular-326","votos":68},{"opcionId":"unica-asamblea-popular-1969","votos":21},{"opcionId":"unica-asamblea-popular-960","votos":15},{"opcionId":"unica-asamblea-popular-13013","votos":9},{"opcionId":"unica-asamblea-popular-3060","votos":9},{"opcionId":"unica-asamblea-popular-vl","votos":7},{"opcionId":"unica-asamblea-popular-101114","votos":5}],"noPartidarios":{"enBlanco":0,"anulados":0,"observados":0}},{"geoId":"Reducto","ganadorOpcionId":"unica-asamblea-popular-326","validos":61,"porOpcion":[{"opcionId":"unica-asamblea-popular-326","votos":29},{"opcionId":"unica-asamblea-popular-1969","votos":11},{"opcionId":"unica-asamblea-popular-960","votos":7},{"opcionId":"unica-asamblea-popular-3060","votos":6},{"opcionId":"unica-asamblea-popular-13013","votos":4},{"opcionId":"unica-asamblea-popular-vl","votos":2},{"opcionId":"unica-asamblea-popular-101114","votos":2}],"noPartidarios":{"enBlanco":0,"anulados":0,"observados":0}},{"geoId":"Jacinto Vera","ganadorOpcionId":"unica-asamblea-popular-326","validos":113,"porOpcion":[{"opcionId":"unica-asamblea-popular-326","votos":57},{"opcionId":"unica-asamblea-popular-1969","votos":20},{"opcionId":"unica-asamblea-popular-3060","votos":15},{"opcionId":"unica-asamblea-popular-960","votos":13},{"opcionId":"unica-asamblea-popular-13013","votos":5},{"opcionId":"unica-asamblea-popular-101114","votos":2},{"opcionId":"unica-asamblea-popular-vl","votos":1}],"noPartidarios":{"enBlanco":0,"anulados":0,"observados":0}},{"geoId":"La Figurita","ganadorOpcionId":"unica-asamblea-popular-326","validos":56,"porOpcion":[{"opcionId":"unica-asamblea-popular-326","votos":32},{"opcionId":"unica-asamblea-popular-960","votos":11},{"opcionId":"unica-asamblea-popular-3060","votos":4},{"opcionId":"unica-asamblea-popular-1969","votos":4},{"opcionId":"unica-asamblea-popular-13013","votos":3},{"opcionId":"unica-asamblea-popular-vl","votos":2}],"noPartidarios":{"enBlanco":0,"anulados":0,"observados":0}},{"geoId":"Atahualpa","ganadorOpcionId":"unica-asamblea-popular-326","validos":114,"porOpcion":[{"opcionId":"unica-asamblea-popular-326","votos":57},{"opcionId":"unica-asamblea-popular-1969","votos":20},{"opcionId":"unica-asamblea-popular-960","votos":14},{"opcionId":"unica-asamblea-popular-3060","votos":10},{"opcionId":"unica-asamblea-popular-vl","votos":6},{"opcionId":"unica-asamblea-popular-13013","votos":4},{"opcionId":"unica-asamblea-popular-101114","votos":3}],"noPartidarios":{"enBlanco":0,"anulados":0,"observados":0}},{"geoId":"Prado, Nueva Savona","ganadorOpcionId":"unica-asamblea-popular-326","validos":390,"porOpcion":[{"opcionId":"unica-asamblea-popular-326","votos":206},{"opcionId":"unica-asamblea-popular-960","votos":51},{"opcionId":"unica-asamblea-popular-3060","votos":48},{"opcionId":"unica-asamblea-popular-1969","votos":47},{"opcionId":"unica-asamblea-popular-13013","votos":19},{"opcionId":"unica-asamblea-popular-vl","votos":14},{"opcionId":"unica-asamblea-popular-101114","votos":5}],"noPartidarios":{"enBlanco":0,"anulados":0,"observados":0}},{"geoId":"Aires Puros","ganadorOpcionId":"unica-asamblea-popular-326","validos":256,"porOpcion":[{"opcionId":"unica-asamblea-popular-326","votos":127},{"opcionId":"unica-asamblea-popular-960","votos":44},{"opcionId":"unica-asamblea-popular-3060","votos":30},{"opcionId":"unica-asamblea-popular-1969","votos":29},{"opcionId":"unica-asamblea-popular-13013","votos":17},{"opcionId":"unica-asamblea-popular-vl","votos":6},{"opcionId":"unica-asamblea-popular-101114","votos":3}],"noPartidarios":{"enBlanco":0,"anulados":0,"observados":0}},{"geoId":"Cerrito","ganadorOpcionId":"unica-asamblea-popular-326","validos":260,"porOpcion":[{"opcionId":"unica-asamblea-popular-326","votos":105},{"opcionId":"unica-asamblea-popular-960","votos":42},{"opcionId":"unica-asamblea-popular-1969","votos":38},{"opcionId":"unica-asamblea-popular-13013","votos":34},{"opcionId":"unica-asamblea-popular-3060","votos":19},{"opcionId":"unica-asamblea-popular-vl","votos":12},{"opcionId":"unica-asamblea-popular-101114","votos":10}],"noPartidarios":{"enBlanco":0,"anulados":0,"observados":0}},{"geoId":"Las Acacias","ganadorOpcionId":"unica-asamblea-popular-326","validos":97,"porOpcion":[{"opcionId":"unica-asamblea-popular-326","votos":47},{"opcionId":"unica-asamblea-popular-960","votos":16},{"opcionId":"unica-asamblea-popular-3060","votos":12},{"opcionId":"unica-asamblea-popular-1969","votos":10},{"opcionId":"unica-asamblea-popular-vl","votos":7},{"opcionId":"unica-asamblea-popular-13013","votos":5}],"noPartidarios":{"enBlanco":0,"anulados":0,"observados":0}},{"geoId":"Casavalle","ganadorOpcionId":"unica-asamblea-popular-326","validos":289,"porOpcion":[{"opcionId":"unica-asamblea-popular-326","votos":143},{"opcionId":"unica-asamblea-popular-960","votos":44},{"opcionId":"unica-asamblea-popular-3060","votos":40},{"opcionId":"unica-asamblea-popular-1969","votos":25},{"opcionId":"unica-asamblea-popular-13013","votos":24},{"opcionId":"unica-asamblea-popular-vl","votos":9},{"opcionId":"unica-asamblea-popular-101114","votos":4}],"noPartidarios":{"enBlanco":0,"anulados":0,"observados":0}},{"geoId":"Manga","ganadorOpcionId":"unica-asamblea-popular-326","validos":74,"porOpcion":[{"opcionId":"unica-asamblea-popular-326","votos":36},{"opcionId":"unica-asamblea-popular-1969","votos":10},{"opcionId":"unica-asamblea-popular-960","votos":10},{"opcionId":"unica-asamblea-popular-3060","votos":8},{"opcionId":"unica-asamblea-popular-13013","votos":5},{"opcionId":"unica-asamblea-popular-vl","votos":4},{"opcionId":"unica-asamblea-popular-101114","votos":1}],"noPartidarios":{"enBlanco":0,"anulados":0,"observados":0}},{"geoId":"Capurro, Bella Vista","ganadorOpcionId":"unica-asamblea-popular-326","validos":229,"porOpcion":[{"opcionId":"unica-asamblea-popular-326","votos":124},{"opcionId":"unica-asamblea-popular-960","votos":34},{"opcionId":"unica-asamblea-popular-1969","votos":27},{"opcionId":"unica-asamblea-popular-3060","votos":23},{"opcionId":"unica-asamblea-popular-vl","votos":9},{"opcionId":"unica-asamblea-popular-13013","votos":7},{"opcionId":"unica-asamblea-popular-101114","votos":5}],"noPartidarios":{"enBlanco":0,"anulados":0,"observados":0}},{"geoId":"Colón Centro y Noroeste","ganadorOpcionId":"unica-asamblea-popular-326","validos":276,"porOpcion":[{"opcionId":"unica-asamblea-popular-326","votos":145},{"opcionId":"unica-asamblea-popular-1969","votos":38},{"opcionId":"unica-asamblea-popular-960","votos":38},{"opcionId":"unica-asamblea-popular-3060","votos":32},{"opcionId":"unica-asamblea-popular-13013","votos":14},{"opcionId":"unica-asamblea-popular-vl","votos":6},{"opcionId":"unica-asamblea-popular-101114","votos":3}],"noPartidarios":{"enBlanco":0,"anulados":0,"observados":0}},{"geoId":"Lezica, Melilla","ganadorOpcionId":"unica-asamblea-popular-326","validos":180,"porOpcion":[{"opcionId":"unica-asamblea-popular-326","votos":103},{"opcionId":"unica-asamblea-popular-1969","votos":28},{"opcionId":"unica-asamblea-popular-960","votos":21},{"opcionId":"unica-asamblea-popular-3060","votos":14},{"opcionId":"unica-asamblea-popular-13013","votos":8},{"opcionId":"unica-asamblea-popular-101114","votos":4},{"opcionId":"unica-asamblea-popular-vl","votos":2}],"noPartidarios":{"enBlanco":0,"anulados":0,"observados":0}},{"geoId":"Colón Sureste, Abayubá","ganadorOpcionId":"unica-asamblea-popular-326","validos":48,"porOpcion":[{"opcionId":"unica-asamblea-popular-326","votos":19},{"opcionId":"unica-asamblea-popular-960","votos":12},{"opcionId":"unica-asamblea-popular-1969","votos":6},{"opcionId":"unica-asamblea-popular-3060","votos":4},{"opcionId":"unica-asamblea-popular-vl","votos":4},{"opcionId":"unica-asamblea-popular-13013","votos":3}],"noPartidarios":{"enBlanco":0,"anulados":0,"observados":0}},{"geoId":"Cerro","ganadorOpcionId":"unica-asamblea-popular-326","validos":294,"porOpcion":[{"opcionId":"unica-asamblea-popular-326","votos":177},{"opcionId":"unica-asamblea-popular-960","votos":46},{"opcionId":"unica-asamblea-popular-1969","votos":31},{"opcionId":"unica-asamblea-popular-3060","votos":19},{"opcionId":"unica-asamblea-popular-13013","votos":11},{"opcionId":"unica-asamblea-popular-vl","votos":7},{"opcionId":"unica-asamblea-popular-101114","votos":3}],"noPartidarios":{"enBlanco":0,"anulados":0,"observados":0}},{"geoId":"La Paloma, Tomkinson","ganadorOpcionId":"unica-asamblea-popular-326","validos":265,"porOpcion":[{"opcionId":"unica-asamblea-popular-326","votos":131},{"opcionId":"unica-asamblea-popular-960","votos":44},{"opcionId":"unica-asamblea-popular-3060","votos":33},{"opcionId":"unica-asamblea-popular-1969","votos":24},{"opcionId":"unica-asamblea-popular-vl","votos":17},{"opcionId":"unica-asamblea-popular-13013","votos":12},{"opcionId":"unica-asamblea-popular-101114","votos":4}],"noPartidarios":{"enBlanco":0,"anulados":0,"observados":0}},{"geoId":"Paso de la Arena","ganadorOpcionId":"unica-asamblea-popular-326","validos":210,"porOpcion":[{"opcionId":"unica-asamblea-popular-326","votos":103},{"opcionId":"unica-asamblea-popular-1969","votos":35},{"opcionId":"unica-asamblea-popular-960","votos":35},{"opcionId":"unica-asamblea-popular-3060","votos":24},{"opcionId":"unica-asamblea-popular-vl","votos":6},{"opcionId":"unica-asamblea-popular-13013","votos":6},{"opcionId":"unica-asamblea-popular-101114","votos":1}],"noPartidarios":{"enBlanco":0,"anulados":0,"observados":0}},{"geoId":"Casabó, Pajas Blancas","ganadorOpcionId":"unica-asamblea-popular-326","validos":272,"porOpcion":[{"opcionId":"unica-asamblea-popular-326","votos":146},{"opcionId":"unica-asamblea-popular-960","votos":37},{"opcionId":"unica-asamblea-popular-1969","votos":28},{"opcionId":"unica-asamblea-popular-3060","votos":27},{"opcionId":"unica-asamblea-popular-vl","votos":13},{"opcionId":"unica-asamblea-popular-101114","votos":12},{"opcionId":"unica-asamblea-popular-13013","votos":9}],"noPartidarios":{"enBlanco":0,"anulados":0,"observados":0}},{"geoId":"La Teja","ganadorOpcionId":"unica-asamblea-popular-326","validos":206,"porOpcion":[{"opcionId":"unica-asamblea-popular-326","votos":111},{"opcionId":"unica-asamblea-popular-960","votos":34},{"opcionId":"unica-asamblea-popular-1969","votos":24},{"opcionId":"unica-asamblea-popular-3060","votos":20},{"opcionId":"unica-asamblea-popular-vl","votos":9},{"opcionId":"unica-asamblea-popular-101114","votos":5},{"opcionId":"unica-asamblea-popular-13013","votos":3}],"noPartidarios":{"enBlanco":0,"anulados":0,"observados":0}},{"geoId":"Tres Ombúes, Victoria","ganadorOpcionId":"unica-asamblea-popular-326","validos":121,"porOpcion":[{"opcionId":"unica-asamblea-popular-326","votos":58},{"opcionId":"unica-asamblea-popular-960","votos":24},{"opcionId":"unica-asamblea-popular-1969","votos":18},{"opcionId":"unica-asamblea-popular-3060","votos":12},{"opcionId":"unica-asamblea-popular-13013","votos":6},{"opcionId":"unica-asamblea-popular-vl","votos":3}],"noPartidarios":{"enBlanco":0,"anulados":0,"observados":0}},{"geoId":"Belvedere","ganadorOpcionId":"unica-asamblea-popular-326","validos":152,"porOpcion":[{"opcionId":"unica-asamblea-popular-326","votos":78},{"opcionId":"unica-asamblea-popular-960","votos":34},{"opcionId":"unica-asamblea-popular-1969","votos":19},{"opcionId":"unica-asamblea-popular-3060","votos":12},{"opcionId":"unica-asamblea-popular-13013","votos":3},{"opcionId":"unica-asamblea-popular-vl","votos":3},{"opcionId":"unica-asamblea-popular-101114","votos":3}],"noPartidarios":{"enBlanco":0,"anulados":0,"observados":0}},{"geoId":"Paso de las Duranas","ganadorOpcionId":"unica-asamblea-popular-326","validos":302,"porOpcion":[{"opcionId":"unica-asamblea-popular-326","votos":152},{"opcionId":"unica-asamblea-popular-960","votos":40},{"opcionId":"unica-asamblea-popular-1969","votos":34},{"opcionId":"unica-asamblea-popular-3060","votos":34},{"opcionId":"unica-asamblea-popular-13013","votos":24},{"opcionId":"unica-asamblea-popular-101114","votos":11},{"opcionId":"unica-asamblea-popular-vl","votos":7}],"noPartidarios":{"enBlanco":0,"anulados":0,"observados":0}},{"geoId":"Nuevo París","ganadorOpcionId":"unica-asamblea-popular-326","validos":299,"porOpcion":[{"opcionId":"unica-asamblea-popular-326","votos":149},{"opcionId":"unica-asamblea-popular-960","votos":49},{"opcionId":"unica-asamblea-popular-1969","votos":40},{"opcionId":"unica-asamblea-popular-3060","votos":31},{"opcionId":"unica-asamblea-popular-13013","votos":21},{"opcionId":"unica-asamblea-popular-vl","votos":7},{"opcionId":"unica-asamblea-popular-101114","votos":2}],"noPartidarios":{"enBlanco":0,"anulados":0,"observados":0}},{"geoId":"Sayago","ganadorOpcionId":"unica-asamblea-popular-326","validos":120,"porOpcion":[{"opcionId":"unica-asamblea-popular-326","votos":61},{"opcionId":"unica-asamblea-popular-1969","votos":26},{"opcionId":"unica-asamblea-popular-3060","votos":13},{"opcionId":"unica-asamblea-popular-960","votos":10},{"opcionId":"unica-asamblea-popular-13013","votos":6},{"opcionId":"unica-asamblea-popular-vl","votos":3},{"opcionId":"unica-asamblea-popular-101114","votos":1}],"noPartidarios":{"enBlanco":0,"anulados":0,"observados":0}},{"geoId":"Conciliación","ganadorOpcionId":"unica-asamblea-popular-326","validos":164,"porOpcion":[{"opcionId":"unica-asamblea-popular-326","votos":85},{"opcionId":"unica-asamblea-popular-960","votos":30},{"opcionId":"unica-asamblea-popular-1969","votos":24},{"opcionId":"unica-asamblea-popular-3060","votos":8},{"opcionId":"unica-asamblea-popular-vl","votos":8},{"opcionId":"unica-asamblea-popular-13013","votos":5},{"opcionId":"unica-asamblea-popular-101114","votos":4}],"noPartidarios":{"enBlanco":0,"anulados":0,"observados":0}}]}