{"eleccionId": "departamentales-2025", "departamento": "rivera", "nivel": "circuito", "escrutinio": "definitivo", "tipo": "departamental", "zonas": [{"geoId": "1", "local": "rivera-L001", "ganadorOpcionId": "colorado", "validos": 226, "porOpcion": [{"opcionId": "colorado", "votos": 141}, {"opcionId": "nacional", "votos": 57}, {"opcionId": "frente-amplio", "votos": 28}], "noPartidarios": {"enBlanco": 0, "anulados": 0, "observados": 0}}, {"geoId": "2", "local": "rivera-L001", "ganadorOpcionId": "colorado", "validos": 297, "porOpcion": [{"opcionId": "colorado", "votos": 189}, {"opcionId": "nacional", "votos": 62}, {"opcionId": "frente-amplio", "votos": 46}], "noPartidarios": {"enBlanco": 0, "anulados": 0, "observados": 0}}, {"geoId": "3", "local": "rivera-L001", "ganadorOpcionId": "colorado", "validos": 314, "porOpcion": [{"opcionId": "colorado", "votos": 177}, {"opcionId": "nacional", "votos": 84}, {"opcionId": "frente-amplio", "votos": 53}], "noPartidarios": {"enBlanco": 0, "anulados": 0, "observados": 0}}, {"geoId": "4", "local": "rivera-L001", "ganadorOpcionId": "colorado", "validos": 305, "porOpcion": [{"opcionId": "colorado", "votos": 194}, {"opcionId": "nacional", "votos": 63}, {"opcionId": "frente-amplio", "votos": 47}, {"opcionId": "asamblea-popular", "votos": 1}], "noPartidarios": {"enBlanco": 0, "anulados": 0, "observados": 0}}, {"geoId": "5", "local": "rivera-L002", "ganadorOpcionId": "colorado", "validos": 290, "porOpcion": [{"opcionId": "colorado", "votos": 156}, {"opcionId": "nacional", "votos": 83}, {"opcionId": "frente-amplio", "votos": 50}, {"opcionId": "asamblea-popular", "votos": 1}], "noPartidarios": {"enBlanco": 0, "anulados": 0, "observados": 0}}, {"geoId": "6", "local": "rivera-L002", "ganadorOpcionId": "colorado", "validos": 310, "porOpcion": [{"opcionId": "colorado", "votos": 174}, {"opcionId": "nacional", "votos": 75}, {"opcionId": "frente-amplio", "votos": 61}], "noPartidarios": {"enBlanco": 0, "anulados": 0, "observados": 0}}, {"geoId": "7", "local": "rivera-L002", "ganadorOpcionId": "colorado", "validos": 307, "porOpcion": [{"opcionId": "colorado", "votos": 160}, {"opcionId": "nacional", "votos": 89}, {"opcionId": "frente-amplio", "votos": 58}], "noPartidarios": {"enBlanco": 0, "anulados": 0, "observados": 0}}, {"geoId": "8", "local": "rivera-L003", "ganadorOpcionId": "colorado", "validos": 277, "porOpcion": [{"opcionId": "colorado", "votos": 172}, {"opcionId": "nacional", "votos": 64}, {"opcionId": "frente-amplio", "votos": 40}, {"opcionId": "asamblea-popular", "votos": 1}], "noPartidarios": {"enBlanco": 0, "anulados": 0, "observados": 0}}, {"geoId": "9", "local": "rivera-L004", "ganadorOpcionId": "colorado", "validos": 307, "porOpcion": [{"opcionId": "colorado", "votos": 169}, {"opcionId": "nacional", "votos": 90}, {"opcionId": "frente-amplio", "votos": 46}, {"opcionId": "asamblea-popular", "votos": 2}], "noPartidarios": {"enBlanco": 0, "anulados": 0, "observados": 0}}, {"geoId": "10", "local": "rivera-L005", "ganadorOpcionId": "colorado", "validos": 289, "porOpcion": [{"opcionId": "colorado", "votos": 163}, {"opcionId": "nacional", "votos": 77}, {"opcionId": "frente-amplio", "votos": 49}], "noPartidarios": {"enBlanco": 0, "anulados": 0, "observados": 0}}, {"geoId": "11", "local": "rivera-L005", "ganadorOpcionId": "colorado", "validos": 297, "porOpcion": [{"opcionId": "colorado", "votos": 177}, {"opcionId": "nacional", "votos": 77}, {"opcionId": "frente-amplio", "votos": 43}], "noPartidarios": {"enBlanco": 0, "anulados": 0, "observados": 0}}, {"geoId": "12", "local": "rivera-L006", "ganadorOpcionId": "colorado", "validos": 280, "porOpcion": [{"opcionId": "colorado", "votos": 157}, {"opcionId": "nacional", "votos": 74}, {"opcionId": "frente-amplio", "votos": 47}, {"opcionId": "asamblea-popular", "votos": 2}], "noPartidarios": {"enBlanco": 0, "anulados": 0, "observados": 0}}, {"geoId": "13", "local": "rivera-L006", "ganadorOpcionId": "colorado", "validos": 286, "porOpcion": [{"opcionId": "colorado", "votos": 166}, {"opcionId": "nacional", "votos": 78}, {"opcionId": "frente-amplio", "votos": 41}, {"opcionId": "asamblea-popular", "votos": 1}], "noPartidarios": {"enBlanco": 0, "anulados": 0, "observados": 0}}, {"geoId": "14", "local": "rivera-L006", "ganadorOpcionId": "colorado", "validos": 294, "porOpcion": [{"opcionId": "colorado", "votos": 166}, {"opcionId": "nacional", "votos": 76}, {"opcionId": "frente-amplio", "votos": 52}], "noPartidarios": {"enBlanco": 0, "anulados": 0, "observados": 0}}, {"geoId": "15", "local": "rivera-L007", "ganadorOpcionId": "colorado", "validos": 276, "porOpcion": [{"opcionId": "colorado", "votos": 155}, {"opcionId": "nacional", "votos": 83}, {"opcionId": "frente-amplio", "votos": 38}], "noPartidarios": {"enBlanco": 0, "anulados": 0, "observados": 0}}, {"geoId": "16", "local": "rivera-L007", "ganadorOpcionId": "colorado", "validos": 271, "porOpcion": [{"opcionId": "colorado", "votos": 139}, {"opcionId": "nacional", "votos": 78}, {"opcionId": "frente-amplio", "votos": 53}, {"opcionId": "asamblea-popular", "votos": 1}], "noPartidarios": {"enBlanco": 0, "anulados": 0, "observados": 0}}, {"geoId": "17", "local": "rivera-L007", "ganadorOpcionId": "colorado", "validos": 288, "porOpcion": [{"opcionId": "colorado", "votos": 145}, {"opcionId": "nacional", "votos": 87}, {"opcionId": "frente-amplio", "votos": 55}, {"opcionId": "asamblea-popular", "votos": 1}], "noPartidarios": {"enBlanco": 0, "anulados": 0, "observados": 0}}, {"geoId": "18", "local": "rivera-L008", "ganadorOpcionId": "colorado", "validos": 294, "porOpcion": [{"opcionId": "colorado", "votos": 147}, {"opcionId": "nacional", "votos": 83}, {"opcionId": "frente-amplio", "votos": 62}, {"opcionId": "asamblea-popular", "votos": 2}], "noPartidarios": {"enBlanco": 0, "anulados": 0, "observados": 0}}, {"geoId": "19", "local": "rivera-L008", "ganadorOpcionId": "colorado", "validos": 308, "porOpcion": [{"opcionId": "colorado", "votos": 164}, {"opcionId": "nacional", "votos": 91}, {"opcionId": "frente-amplio", "votos": 53}], "noPartidarios": {"enBlanco": 0, "anulados": 0, "observados": 0}}, {"geoId": "20", "local": "rivera-L008", "ganadorOpcionId": "colorado", "validos": 307, "porOpcion": [{"opcionId": "colorado", "votos": 170}, {"opcionId": "nacional", "votos": 72}, {"opcionId": "frente-amplio", "votos": 62}, {"opcionId": "asamblea-popular", "votos": 3}], "noPartidarios": {"enBlanco": 0, "anulados": 0, "observados": 0}}, {"geoId": "21", "local": "rivera-L009", "ganadorOpcionId": "colorado", "validos": 192, "porOpcion": [{"opcionId": "colorado", "votos": 111}, {"opcionId": "nacional", "votos": 54}, {"opcionId": "frente-amplio", "votos": 26}, {"opcionId": "asamblea-popular", "votos": 1}], "noPartidarios": {"enBlanco": 0, "anulados": 0, "observados": 0}}, {"geoId": "22", "local": "rivera-L009", "ganadorOpcionId": "colorado", "validos": 263, "porOpcion": [{"opcionId": "colorado", "votos": 164}, {"opcionId": "nacional", "votos": 62}, {"opcionId": "frente-amplio", "votos": 37}], "noPartidarios": {"enBlanco": 0, "anulados": 0, "observados": 0}}, {"geoId": "23", "local": "rivera-L009", "ganadorOpcionId": "colorado", "validos": 272, "porOpcion": [{"opcionId": "colorado", "votos": 177}, {"opcionId": "nacional", "votos": 55}, {"opcionId": "frente-amplio", "votos": 40}], "noPartidarios": {"enBlanco": 0, "anulados": 0, "observados": 0}}, {"geoId": "24", "local": "rivera-L010", "ganadorOpcionId": "colorado", "validos": 301, "porOpcion": [{"opcionId": "colorado", "votos": 191}, {"opcionId": "nacional", "votos": 75}, {"opcionId": "frente-amplio", "votos": 34}, {"opcionId": "asamblea-popular", "votos": 1}], "noPartidarios": {"enBlanco": 0, "anulados": 0, "observados": 0}}, {"geoId": "25", "local": "rivera-L010", "ganadorOpcionId": "colorado", "validos": 323, "porOpcion": [{"opcionId": "colorado", "votos": 194}, {"opcionId": "nacional", "votos": 76}, {"opcionId": "frente-amplio", "votos": 53}], "noPartidarios": {"enBlanco": 0, "anulados": 0, "observados": 0}}, {"geoId": "26", "local": "rivera-L010", "ganadorOpcionId": "colorado", "validos": 326, "porOpcion": [{"opcionId": "colorado", "votos": 219}, {"opcionId": "nacional", "votos": 64}, {"opcionId": "frente-amplio", "votos": 39}, {"opcionId": "asamblea-popular", "votos": 4}], "noPartidarios": {"enBlanco": 0, "anulados": 0, "observados": 0}}, {"geoId": "27", "local": "rivera-L010", "ganadorOpcionId": "colorado", "validos": 319, "porOpcion": [{"opcionId": "colorado", "votos": 200}, {"opcionId": "nacional", "votos": 66}, {"opcionId": "frente-amplio", "votos": 51}, {"opcionId": "asamblea-popular", "votos": 2}], "noPartidarios": {"enBlanco": 0, "anulados": 0, "observados": 0}}, {"geoId": "28", "local": "rivera-L010", "ganadorOpcionId": "colorado", "validos": 337, "porOpcion": [{"opcionId": "colorado", "votos": 187}, {"opcionId": "nacional", "votos": 92}, {"opcionId": "frente-amplio", "votos": 57}, {"opcionId": "asamblea-popular", "votos": 1}], "noPartidarios": {"enBlanco": 0, "anulados": 0, "observados": 0}}, {"geoId": "29", "local": "rivera-L010", "ganadorOpcionId": "colorado", "validos": 321, "porOpcion": [{"opcionId": "colorado", "votos": 195}, {"opcionId": "nacional", "votos": 65}, {"opcionId": "frente-amplio", "votos": 61}], "noPartidarios": {"enBlanco": 0, "anulados": 0, "observados": 0}}, {"geoId": "30", "local": "rivera-L010", "ganadorOpcionId": "colorado", "validos": 324, "porOpcion": [{"opcionId": "colorado", "votos": 204}, {"opcionId": "nacional", "votos": 61}, {"opcionId": "frente-amplio", "votos": 58}, {"opcionId": "asamblea-popular", "votos": 1}], "noPartidarios": {"enBlanco": 0, "anulados": 0, "observados": 0}}, {"geoId": "31", "local": "rivera-L010", "ganadorOpcionId": "colorado", "validos": 330, "porOpcion": [{"opcionId": "colorado", "votos": 185}, {"opcionId": "nacional", "votos": 82}, {"opcionId": "frente-amplio", "votos": 61}, {"opcionId": "asamblea-popular", "votos": 2}], "noPartidarios": {"enBlanco": 0, "anulados": 0, "observados": 0}}, {"geoId": "32", "local": "rivera-L010", "ganadorOpcionId": "colorado", "validos": 325, "porOpcion": [{"opcionId": "colorado", "votos": 183}, {"opcionId": "nacional", "votos": 76}, {"opcionId": "frente-amplio", "votos": 66}], "noPartidarios": {"enBlanco": 0, "anulados": 0, "observados": 0}}, {"geoId": "33", "local": "rivera-L011", "ganadorOpcionId": "colorado", "validos": 328, "porOpcion": [{"opcionId": "colorado", "votos": 205}, {"opcionId": "nacional", "votos": 65}, {"opcionId": "frente-amplio", "votos": 58}], "noPartidarios": {"enBlanco": 0, "anulados": 0, "observados": 0}}, {"geoId": "34", "local": "rivera-L011", "ganadorOpcionId": "colorado", "validos": 320, "porOpcion": [{"opcionId": "colorado", "votos": 183}, {"opcionId": "frente-amplio", "votos": 73}, {"opcionId": "nacional", "votos": 64}], "noPartidarios": {"enBlanco": 0, "anulados": 0, "observados": 0}}, {"geoId": "35", "local": "rivera-L011", "ganadorOpcionId": "colorado", "validos": 327, "porOpcion": [{"opcionId": "colorado", "votos": 191}, {"opcionId": "nacional", "votos": 82}, {"opcionId": "frente-amplio", "votos": 53}, {"opcionId": "asamblea-popular", "votos": 1}], "noPartidarios": {"enBlanco": 0, "anulados": 0, "observados": 0}}, {"geoId": "36", "local": "rivera-L011", "ganadorOpcionId": "colorado", "validos": 329, "porOpcion": [{"opcionId": "colorado", "votos": 207}, {"opcionId": "nacional", "votos": 71}, {"opcionId": "frente-amplio", "votos": 50}, {"opcionId": "asamblea-popular", "votos": 1}], "noPartidarios": {"enBlanco": 0, "anulados": 0, "observados": 0}}, {"geoId": "37", "local": "rivera-L011", "ganadorOpcionId": "colorado", "validos": 323, "porOpcion": [{"opcionId": "colorado", "votos": 207}, {"opcionId": "nacional", "votos": 69}, {"opcionId": "frente-amplio", "votos": 46}, {"opcionId": "asamblea-popular", "votos": 1}], "noPartidarios": {"enBlanco": 0, "anulados": 0, "observados": 0}}, {"geoId": "38", "local": "rivera-L011", "ganadorOpcionId": "colorado", "validos": 316, "porOpcion": [{"opcionId": "colorado", "votos": 186}, {"opcionId": "nacional", "votos": 74}, {"opcionId": "frente-amplio", "votos": 54}, {"opcionId": "asamblea-popular", "votos": 2}], "noPartidarios": {"enBlanco": 0, "anulados": 0, "observados": 0}}, {"geoId": "39", "local": "rivera-L012", "ganadorOpcionId": "colorado", "validos": 317, "porOpcion": [{"opcionId": "colorado", "votos": 194}, {"opcionId": "nacional", "votos": 73}, {"opcionId": "frente-amplio", "votos": 50}], "noPartidarios": {"enBlanco": 0, "anulados": 0, "observados": 0}}, {"geoId": "40", "local": "rivera-L012", "ganadorOpcionId": "colorado", "validos": 329, "porOpcion": [{"opcionId": "colorado", "votos": 211}, {"opcionId": "nacional", "votos": 78}, {"opcionId": "frente-amplio", "votos": 39}, {"opcionId": "asamblea-popular", "votos": 1}], "noPartidarios": {"enBlanco": 0, "anulados": 0, "observados": 0}}, {"geoId": "41", "local": "rivera-L012", "ganadorOpcionId": "colorado", "validos": 325, "porOpcion": [{"opcionId": "colorado", "votos": 205}, {"opcionId": "nacional", "votos": 71}, {"opcionId": "frente-amplio", "votos": 48}, {"opcionId": "asamblea-popular", "votos": 1}], "noPartidarios": {"enBlanco": 0, "anulados": 0, "observados": 0}}, {"geoId": "42", "local": "rivera-L012", "ganadorOpcionId": "colorado", "validos": 311, "porOpcion": [{"opcionId": "colorado", "votos": 183}, {"opcionId": "nacional", "votos": 77}, {"opcionId": "frente-amplio", "votos": 50}, {"opcionId": "asamblea-popular", "votos": 1}], "noPartidarios": {"enBlanco": 0, "anulados": 0, "observados": 0}}, {"geoId": "43", "local": "rivera-L012", "ganadorOpcionId": "colorado", "validos": 301, "porOpcion": [{"opcionId": "colorado", "votos": 174}, {"opcionId": "nacional", "votos": 70}, {"opcionId": "frente-amplio", "votos": 56}, {"opcionId": "asamblea-popular", "votos": 1}], "noPartidarios": {"enBlanco": 0, "anulados": 0, "observados": 0}}, {"geoId": "44", "local": "rivera-L013", "ganadorOpcionId": "colorado", "validos": 310, "porOpcion": [{"opcionId": "colorado", "votos": 171}, {"opcionId": "nacional", "votos": 88}, {"opcionId": "frente-amplio", "votos": 51}], "noPartidarios": {"enBlanco": 0, "anulados": 0, "observados": 0}}, {"geoId": "45", "local": "rivera-L013", "ganadorOpcionId": "colorado", "validos": 316, "porOpcion": [{"opcionId": "colorado", "votos": 186}, {"opcionId": "nacional", "votos": 79}, {"opcionId": "frente-amplio", "votos": 51}], "noPartidarios": {"enBlanco": 0, "anulados": 0, "observados": 0}}, {"geoId": "46", "local": "rivera-L013", "ganadorOpcionId": "colorado", "validos": 322, "porOpcion": [{"opcionId": "colorado", "votos": 196}, {"opcionId": "nacional", "votos": 72}, {"opcionId": "frente-amplio", "votos": 50}, {"opcionId": "asamblea-popular", "votos": 4}], "noPartidarios": {"enBlanco": 0, "anulados": 0, "observados": 0}}, {"geoId": "47", "local": "rivera-L013", "ganadorOpcionId": "colorado", "validos": 325, "porOpcion": [{"opcionId": "colorado", "votos": 201}, {"opcionId": "nacional", "votos": 71}, {"opcionId": "frente-amplio", "votos": 52}, {"opcionId": "asamblea-popular", "votos": 1}], "noPartidarios": {"enBlanco": 0, "anulados": 0, "observados": 0}}, {"geoId": "48", "local": "rivera-L013", "ganadorOpcionId": "colorado", "validos": 304, "porOpcion": [{"opcionId": "colorado", "votos": 178}, {"opcionId": "nacional", "votos": 76}, {"opcionId": "frente-amplio", "votos": 49}, {"opcionId": "asamblea-popular", "votos": 1}], "noPartidarios": {"enBlanco": 0, "anulados": 0, "observados": 0}}, {"geoId": "49", "local": "rivera-L013", "ganadorOpcionId": "colorado", "validos": 322, "porOpcion": [{"opcionId": "colorado", "votos": 201}, {"opcionId": "nacional", "votos": 77}, {"opcionId": "frente-amplio", "votos": 41}, {"opcionId": "asamblea-popular", "votos": 3}], "noPartidarios": {"enBlanco": 0, "anulados": 0, "observados": 0}}, {"geoId": "50", "local": "rivera-L014", "ganadorOpcionId": "colorado", "validos": 307, "porOpcion": [{"opcionId": "colorado", "votos": 196}, {"opcionId": "nacional", "votos": 80}, {"opcionId": "frente-amplio", "votos": 30}, {"opcionId": "asamblea-popular", "votos": 1}], "noPartidarios": {"enBlanco": 0, "anulados": 0, "observados": 0}}, {"geoId": "51", "local": "rivera-L014", "ganadorOpcionId": "colorado", "validos": 308, "porOpcion": [{"opcionId": "colorado", "votos": 189}, {"opcionId": "nacional", "votos": 72}, {"opcionId": "frente-amplio", "votos": 47}], "noPartidarios": {"enBlanco": 0, "anulados": 0, "observados": 0}}, {"geoId": "52", "local": "rivera-L014", "ganadorOpcionId": "colorado", "validos": 308, "porOpcion": [{"opcionId": "colorado", "votos": 188}, {"opcionId": "nacional", "votos": 75}, {"opcionId": "frente-amplio", "votos": 39}, {"opcionId": "asamblea-popular", "votos": 6}], "noPartidarios": {"enBlanco": 0, "anulados": 0, "observados": 0}}, {"geoId": "53", "local": "rivera-L014", "ganadorOpcionId": "colorado", "validos": 302, "porOpcion": [{"opcionId": "colorado", "votos": 200}, {"opcionId": "nacional", "votos": 60}, {"opcionId": "frente-amplio", "votos": 42}], "noPartidarios": {"enBlanco": 0, "anulados": 0, "observados": 0}}, {"geoId": "54", "local": "rivera-L014", "ganadorOpcionId": "colorado", "validos": 316, "porOpcion": [{"opcionId": "colorado", "votos": 184}, {"opcionId": "nacional", "votos": 86}, {"opcionId": "frente-amplio", "votos": 44}, {"opcionId": "asamblea-popular", "votos": 2}], "noPartidarios": {"enBlanco": 0, "anulados": 0, "observados": 0}}, {"geoId": "55", "local": "rivera-L014", "ganadorOpcionId": "colorado", "validos": 316, "porOpcion": [{"opcionId": "colorado", "votos": 192}, {"opcionId": "nacional", "votos": 66}, {"opcionId": "frente-amplio", "votos": 56}, {"opcionId": "asamblea-popular", "votos": 2}], "noPartidarios": {"enBlanco": 0, "anulados": 0, "observados": 0}}, {"geoId": "56", "local": "rivera-L014", "ganadorOpcionId": "colorado", "validos": 300, "porOpcion": [{"opcionId": "colorado", "votos": 203}, {"opcionId": "nacional", "votos": 61}, {"opcionId": "frente-amplio", "votos": 36}], "noPartidarios": {"enBlanco": 0, "anulados": 0, "observados": 0}}, {"geoId": "57", "local": "rivera-L015", "ganadorOpcionId": "colorado", "validos": 296, "porOpcion": [{"opcionId": "colorado", "votos": 184}, {"opcionId": "nacional", "votos": 67}, {"opcionId": "frente-amplio", "votos": 45}], "noPartidarios": {"enBlanco": 0, "anulados": 0, "observados": 0}}, {"geoId": "58", "local": "rivera-L015", "ganadorOpcionId": "colorado", "validos": 289, "porOpcion": [{"opcionId": "colorado", "votos": 173}, {"opcionId": "nacional", "votos": 61}, {"opcionId": "frente-amplio", "votos": 53}, {"opcionId": "asamblea-popular", "votos": 2}], "noPartidarios": {"enBlanco": 0, "anulados": 0, "observados": 0}}, {"geoId": "59", "local": "rivera-L016", "ganadorOpcionId": "colorado", "validos": 296, "porOpcion": [{"opcionId": "colorado", "votos": 168}, {"opcionId": "nacional", "votos": 93}, {"opcionId": "frente-amplio", "votos": 31}, {"opcionId": "asamblea-popular", "votos": 4}], "noPartidarios": {"enBlanco": 0, "anulados": 0, "observados": 0}}, {"geoId": "60", "local": "rivera-L016", "ganadorOpcionId": "colorado", "validos": 300, "porOpcion": [{"opcionId": "colorado", "votos": 177}, {"opcionId": "nacional", "votos": 74}, {"opcionId": "frente-amplio", "votos": 48}, {"opcionId": "asamblea-popular", "votos": 1}], "noPartidarios": {"enBlanco": 0, "anulados": 0, "observados": 0}}, {"geoId": "61", "local": "rivera-L016", "ganadorOpcionId": "colorado", "validos": 313, "porOpcion": [{"opcionId": "colorado", "votos": 203}, {"opcionId": "nacional", "votos": 71}, {"opcionId": "frente-amplio", "votos": 39}], "noPartidarios": {"enBlanco": 0, "anulados": 0, "observados": 0}}, {"geoId": "62", "local": "rivera-L016", "ganadorOpcionId": "colorado", "validos": 309, "porOpcion": [{"opcionId": "colorado", "votos": 189}, {"opcionId": "nacional", "votos": 67}, {"opcionId": "frente-amplio", "votos": 53}], "noPartidarios": {"enBlanco": 0, "anulados": 0, "observados": 0}}, {"geoId": "63", "local": "rivera-L017", "ganadorOpcionId": "colorado", "validos": 288, "porOpcion": [{"opcionId": "colorado", "votos": 188}, {"opcionId": "nacional", "votos": 51}, {"opcionId": "frente-amplio", "votos": 46}, {"opcionId": "asamblea-popular", "votos": 3}], "noPartidarios": {"enBlanco": 0, "anulados": 0, "observados": 0}}, {"geoId": "64", "local": "rivera-L017", "ganadorOpcionId": "colorado", "validos": 301, "porOpcion": [{"opcionId": "colorado", "votos": 181}, {"opcionId": "nacional", "votos": 75}, {"opcionId": "frente-amplio", "votos": 45}], "noPartidarios": {"enBlanco": 0, "anulados": 0, "observados": 0}}, {"geoId": "65", "local": "rivera-L018", "ganadorOpcionId": "colorado", "validos": 300, "porOpcion": [{"opcionId": "colorado", "votos": 148}, {"opcionId": "nacional", "votos": 98}, {"opcionId": "frente-amplio", "votos": 50}, {"opcionId": "asamblea-popular", "votos": 4}], "noPartidarios": {"enBlanco": 0, "anulados": 0, "observados": 0}}, {"geoId": "66", "local": "rivera-L018", "ganadorOpcionId": "colorado", "validos": 318, "porOpcion": [{"opcionId": "colorado", "votos": 201}, {"opcionId": "nacional", "votos": 77}, {"opcionId": "frente-amplio", "votos": 40}], "noPartidarios": {"enBlanco": 0, "anulados": 0, "observados": 0}}, {"geoId": "67", "local": "rivera-L018", "ganadorOpcionId": "colorado", "validos": 285, "porOpcion": [{"opcionId": "colorado", "votos": 165}, {"opcionId": "nacional", "votos": 79}, {"opcionId": "frente-amplio", "votos": 39}, {"opcionId": "asamblea-popular", "votos": 2}], "noPartidarios": {"enBlanco": 0, "anulados": 0, "observados": 0}}, {"geoId": "68", "local": "rivera-L018", "ganadorOpcionId": "colorado", "validos": 303, "porOpcion": [{"opcionId": "colorado", "votos": 186}, {"opcionId": "nacional", "votos": 76}, {"opcionId": "frente-amplio", "votos": 41}], "noPartidarios": {"enBlanco": 0, "anulados": 0, "observados": 0}}, {"geoId": "69", "local": "rivera-L018", "ganadorOpcionId": "colorado", "validos": 306, "porOpcion": [{"opcionId": "colorado", "votos": 188}, {"opcionId": "nacional", "votos": 65}, {"opcionId": "frente-amplio", "votos": 51}, {"opcionId": "asamblea-popular", "votos": 2}], "noPartidarios": {"enBlanco": 0, "anulados": 0, "observados": 0}}, {"geoId": "70", "local": "rivera-L018", "ganadorOpcionId": "colorado", "validos": 307, "porOpcion": [{"opcionId": "colorado", "votos": 183}, {"opcionId": "nacional", "votos": 80}, {"opcionId": "frente-amplio", "votos": 44}], "noPartidarios": {"enBlanco": 0, "anulados": 0, "observados": 0}}, {"geoId": "71", "local": "rivera-L019", "ganadorOpcionId": "colorado", "validos": 317, "porOpcion": [{"opcionId": "colorado", "votos": 185}, {"opcionId": "nacional", "votos": 74}, {"opcionId": "frente-amplio", "votos": 57}, {"opcionId": "asamblea-popular", "votos": 1}], "noPartidarios": {"enBlanco": 0, "anulados": 0, "observados": 0}}, {"geoId": "72", "local": "rivera-L019", "ganadorOpcionId": "colorado", "validos": 322, "porOpcion": [{"opcionId": "colorado", "votos": 204}, {"opcionId": "nacional", "votos": 61}, {"opcionId": "frente-amplio", "votos": 55}, {"opcionId": "asamblea-popular", "votos": 2}], "noPartidarios": {"enBlanco": 0, "anulados": 0, "observados": 0}}, {"geoId": "73", "local": "rivera-L020", "ganadorOpcionId": "colorado", "validos": 314, "porOpcion": [{"opcionId": "colorado", "votos": 179}, {"opcionId": "nacional", "votos": 84}, {"opcionId": "frente-amplio", "votos": 49}, {"opcionId": "asamblea-popular", "votos": 2}], "noPartidarios": {"enBlanco": 0, "anulados": 0, "observados": 0}}, {"geoId": "74", "local": "rivera-L020", "ganadorOpcionId": "colorado", "validos": 327, "porOpcion": [{"opcionId": "colorado", "votos": 178}, {"opcionId": "nacional", "votos": 103}, {"opcionId": "frente-amplio", "votos": 43}, {"opcionId": "asamblea-popular", "votos": 3}], "noPartidarios": {"enBlanco": 0, "anulados": 0, "observados": 0}}, {"geoId": "75", "local": "rivera-L020", "ganadorOpcionId": "colorado", "validos": 303, "porOpcion": [{"opcionId": "colorado", "votos": 174}, {"opcionId": "nacional", "votos": 77}, {"opcionId": "frente-amplio", "votos": 52}], "noPartidarios": {"enBlanco": 0, "anulados": 0, "observados": 0}}, {"geoId": "76", "local": "rivera-L021", "ganadorOpcionId": "colorado", "validos": 231, "porOpcion": [{"opcionId": "colorado", "votos": 152}, {"opcionId": "nacional", "votos": 49}, {"opcionId": "frente-amplio", "votos": 30}], "noPartidarios": {"enBlanco": 0, "anulados": 0, "observados": 0}}, {"geoId": "77", "local": "rivera-L021", "ganadorOpcionId": "colorado", "validos": 301, "porOpcion": [{"opcionId": "colorado", "votos": 196}, {"opcionId": "nacional", "votos": 67}, {"opcionId": "frente-amplio", "votos": 38}], "noPartidarios": {"enBlanco": 0, "anulados": 0, "observados": 0}}, {"geoId": "78", "local": "rivera-L021", "ganadorOpcionId": "colorado", "validos": 345, "porOpcion": [{"opcionId": "colorado", "votos": 214}, {"opcionId": "nacional", "votos": 72}, {"opcionId": "frente-amplio", "votos": 59}], "noPartidarios": {"enBlanco": 0, "anulados": 0, "observados": 0}}, {"geoId": "79", "local": "rivera-L021", "ganadorOpcionId": "colorado", "validos": 320, "porOpcion": [{"opcionId": "colorado", "votos": 189}, {"opcionId": "frente-amplio", "votos": 66}, {"opcionId": "nacional", "votos": 63}, {"opcionId": "asamblea-popular", "votos": 2}], "noPartidarios": {"enBlanco": 0, "anulados": 0, "observados": 0}}, {"geoId": "80", "local": "rivera-L021", "ganadorOpcionId": "colorado", "validos": 327, "porOpcion": [{"opcionId": "colorado", "votos": 223}, {"opcionId": "frente-amplio", "votos": 57}, {"opcionId": "nacional", "votos": 47}], "noPartidarios": {"enBlanco": 0, "anulados": 0, "observados": 0}}, {"geoId": "81", "local": "rivera-L022", "ganadorOpcionId": "colorado", "validos": 333, "porOpcion": [{"opcionId": "colorado", "votos": 210}, {"opcionId": "frente-amplio", "votos": 66}, {"opcionId": "nacional", "votos": 57}], "noPartidarios": {"enBlanco": 0, "anulados": 0, "observados": 0}}, {"geoId": "82", "local": "rivera-L022", "ganadorOpcionId": "colorado", "validos": 316, "porOpcion": [{"opcionId": "colorado", "votos": 171}, {"opcionId": "frente-amplio", "votos": 73}, {"opcionId": "nacional", "votos": 72}], "noPartidarios": {"enBlanco": 0, "anulados": 0, "observados": 0}}, {"geoId": "83", "local": "rivera-L022", "ganadorOpcionId": "colorado", "validos": 327, "porOpcion": [{"opcionId": "colorado", "votos": 193}, {"opcionId": "nacional", "votos": 75}, {"opcionId": "frente-amplio", "votos": 59}], "noPartidarios": {"enBlanco": 0, "anulados": 0, "observados": 0}}, {"geoId": "84", "local": "rivera-L022", "ganadorOpcionId": "colorado", "validos": 330, "porOpcion": [{"opcionId": "colorado", "votos": 211}, {"opcionId": "nacional", "votos": 64}, {"opcionId": "frente-amplio", "votos": 55}], "noPartidarios": {"enBlanco": 0, "anulados": 0, "observados": 0}}, {"geoId": "85", "local": "rivera-L023", "ganadorOpcionId": "colorado", "validos": 321, "porOpcion": [{"opcionId": "colorado", "votos": 193}, {"opcionId": "nacional", "votos": 73}, {"opcionId": "frente-amplio", "votos": 54}, {"opcionId": "asamblea-popular", "votos": 1}], "noPartidarios": {"enBlanco": 0, "anulados": 0, "observados": 0}}, {"geoId": "86", "local": "rivera-L023", "ganadorOpcionId": "colorado", "validos": 329, "porOpcion": [{"opcionId": "colorado", "votos": 201}, {"opcionId": "nacional", "votos": 71}, {"opcionId": "frente-amplio", "votos": 57}], "noPartidarios": {"enBlanco": 0, "anulados": 0, "observados": 0}}, {"geoId": "87", "local": "rivera-L023", "ganadorOpcionId": "colorado", "validos": 324, "porOpcion": [{"opcionId": "colorado", "votos": 197}, {"opcionId": "nacional", "votos": 67}, {"opcionId": "frente-amplio", "votos": 59}, {"opcionId": "asamblea-popular", "votos": 1}], "noPartidarios": {"enBlanco": 0, "anulados": 0, "observados": 0}}, {"geoId": "88", "local": "rivera-L024", "ganadorOpcionId": "colorado", "validos": 300, "porOpcion": [{"opcionId": "colorado", "votos": 185}, {"opcionId": "nacional", "votos": 65}, {"opcionId": "frente-amplio", "votos": 47}, {"opcionId": "asamblea-popular", "votos": 3}], "noPartidarios": {"enBlanco": 0, "anulados": 0, "observados": 0}}, {"geoId": "89", "local": "rivera-L024", "ganadorOpcionId": "colorado", "validos": 324, "porOpcion": [{"opcionId": "colorado", "votos": 196}, {"opcionId": "nacional", "votos": 84}, {"opcionId": "frente-amplio", "votos": 44}], "noPartidarios": {"enBlanco": 0, "anulados": 0, "observados": 0}}, {"geoId": "90", "local": "rivera-L024", "ganadorOpcionId": "colorado", "validos": 334, "porOpcion": [{"opcionId": "colorado", "votos": 212}, {"opcionId": "nacional", "votos": 69}, {"opcionId": "frente-amplio", "votos": 53}], "noPartidarios": {"enBlanco": 0, "anulados": 0, "observados": 0}}, {"geoId": "91", "local": "rivera-L024", "ganadorOpcionId": "colorado", "validos": 317, "porOpcion": [{"opcionId": "colorado", "votos": 181}, {"opcionId": "nacional", "votos": 80}, {"opcionId": "frente-amplio", "votos": 54}, {"opcionId": "asamblea-popular", "votos": 2}], "noPartidarios": {"enBlanco": 0, "anulados": 0, "observados": 0}}, {"geoId": "92", "local": "rivera-L024", "ganadorOpcionId": "colorado", "validos": 310, "porOpcion": [{"opcionId": "colorado", "votos": 196}, {"opcionId": "nacional", "votos": 77}, {"opcionId": "frente-amplio", "votos": 37}], "noPartidarios": {"enBlanco": 0, "anulados": 0, "observados": 0}}, {"geoId": "93", "local": "rivera-L025", "ganadorOpcionId": "colorado", "validos": 315, "porOpcion": [{"opcionId": "colorado", "votos": 206}, {"opcionId": "nacional", "votos": 59}, {"opcionId": "frente-amplio", "votos": 50}], "noPartidarios": {"enBlanco": 0, "anulados": 0, "observados": 0}}, {"geoId": "94", "local": "rivera-L025", "ganadorOpcionId": "colorado", "validos": 311, "porOpcion": [{"opcionId": "colorado", "votos": 199}, {"opcionId": "nacional", "votos": 59}, {"opcionId": "frente-amplio", "votos": 53}], "noPartidarios": {"enBlanco": 0, "anulados": 0, "observados": 0}}, {"geoId": "95", "local": "rivera-L026", "ganadorOpcionId": "colorado", "validos": 321, "porOpcion": [{"opcionId": "colorado", "votos": 204}, {"opcionId": "nacional", "votos": 60}, {"opcionId": "frente-amplio", "votos": 56}, {"opcionId": "asamblea-popular", "votos": 1}], "noPartidarios": {"enBlanco": 0, "anulados": 0, "observados": 0}}, {"geoId": "96", "local": "rivera-L026", "ganadorOpcionId": "colorado", "validos": 330, "porOpcion": [{"opcionId": "colorado", "votos": 189}, {"opcionId": "nacional", "votos": 74}, {"opcionId": "frente-amplio", "votos": 67}], "noPartidarios": {"enBlanco": 0, "anulados": 0, "observados": 0}}, {"geoId": "97", "local": "rivera-L026", "ganadorOpcionId": "colorado", "validos": 324, "porOpcion": [{"opcionId": "colorado", "votos": 207}, {"opcionId": "nacional", "votos": 73}, {"opcionId": "frente-amplio", "votos": 44}], "noPartidarios": {"enBlanco": 0, "anulados": 0, "observados": 0}}, {"geoId": "98", "local": "rivera-L026", "ganadorOpcionId": "colorado", "validos": 320, "porOpcion": [{"opcionId": "colorado", "votos": 217}, {"opcionId": "nacional", "votos": 52}, {"opcionId": "frente-amplio", "votos": 50}, {"opcionId": "asamblea-popular", "votos": 1}], "noPartidarios": {"enBlanco": 0, "anulados": 0, "observados": 0}}, {"geoId": "99", "local": "rivera-L027", "ganadorOpcionId": "colorado", "validos": 309, "porOpcion": [{"opcionId": "colorado", "votos": 176}, {"opcionId": "nacional", "votos": 80}, {"opcionId": "frente-amplio", "votos": 52}, {"opcionId": "asamblea-popular", "votos": 1}], "noPartidarios": {"enBlanco": 0, "anulados": 0, "observados": 0}}, {"geoId": "100", "local": "rivera-L027", "ganadorOpcionId": "colorado", "validos": 306, "porOpcion": [{"opcionId": "colorado", "votos": 177}, {"opcionId": "nacional", "votos": 74}, {"opcionId": "frente-amplio", "votos": 52}, {"opcionId": "asamblea-popular", "votos": 3}], "noPartidarios": {"enBlanco": 0, "anulados": 0, "observados": 0}}, {"geoId": "101", "local": "rivera-L027", "ganadorOpcionId": "colorado", "validos": 311, "porOpcion": [{"opcionId": "colorado", "votos": 182}, {"opcionId": "nacional", "votos": 85}, {"opcionId": "frente-amplio", "votos": 44}], "noPartidarios": {"enBlanco": 0, "anulados": 0, "observados": 0}}, {"geoId": "102", "local": "rivera-L027", "ganadorOpcionId": "colorado", "validos": 302, "porOpcion": [{"opcionId": "colorado", "votos": 171}, {"opcionId": "nacional", "votos": 79}, {"opcionId": "frente-amplio", "votos": 51}, {"opcionId": "asamblea-popular", "votos": 1}], "noPartidarios": {"enBlanco": 0, "anulados": 0, "observados": 0}}, {"geoId": "103", "local": "rivera-L027", "ganadorOpcionId": "colorado", "validos": 326, "porOpcion": [{"opcionId": "colorado", "votos": 204}, {"opcionId": "nacional", "votos": 71}, {"opcionId": "frente-amplio", "votos": 51}], "noPartidarios": {"enBlanco": 0, "anulados": 0, "observados": 0}}, {"geoId": "104", "local": "rivera-L027", "ganadorOpcionId": "colorado", "validos": 327, "porOpcion": [{"opcionId": "colorado", "votos": 195}, {"opcionId": "nacional", "votos": 81}, {"opcionId": "frente-amplio", "votos": 51}], "noPartidarios": {"enBlanco": 0, "anulados": 0, "observados": 0}}, {"geoId": "105", "local": "rivera-L027", "ganadorOpcionId": "colorado", "validos": 324, "porOpcion": [{"opcionId": "colorado", "votos": 197}, {"opcionId": "frente-amplio", "votos": 64}, {"opcionId": "nacional", "votos": 63}], "noPartidarios": {"enBlanco": 0, "anulados": 0, "observados": 0}}, {"geoId": "106", "local": "rivera-L028", "ganadorOpcionId": "colorado", "validos": 324, "porOpcion": [{"opcionId": "colorado", "votos": 199}, {"opcionId": "nacional", "votos": 75}, {"opcionId": "frente-amplio", "votos": 50}], "noPartidarios": {"enBlanco": 0, "anulados": 0, "observados": 0}}, {"geoId": "107", "local": "rivera-L028", "ganadorOpcionId": "colorado", "validos": 345, "porOpcion": [{"opcionId": "colorado", "votos": 213}, {"opcionId": "nacional", "votos": 73}, {"opcionId": "frente-amplio", "votos": 58}, {"opcionId": "asamblea-popular", "votos": 1}], "noPartidarios": {"enBlanco": 0, "anulados": 0, "observados": 0}}, {"geoId": "108", "local": "rivera-L028", "ganadorOpcionId": "colorado", "validos": 334, "porOpcion": [{"opcionId": "colorado", "votos": 212}, {"opcionId": "nacional", "votos": 66}, {"opcionId": "frente-amplio", "votos": 56}], "noPartidarios": {"enBlanco": 0, "anulados": 0, "observados": 0}}, {"geoId": "109", "local": "rivera-L028", "ganadorOpcionId": "colorado", "validos": 331, "porOpcion": [{"opcionId": "colorado", "votos": 219}, {"opcionId": "nacional", "votos": 60}, {"opcionId": "frente-amplio", "votos": 52}], "noPartidarios": {"enBlanco": 0, "anulados": 0, "observados": 0}}, {"geoId": "110", "local": "rivera-L028", "ganadorOpcionId": "colorado", "validos": 334, "porOpcion": [{"opcionId": "colorado", "votos": 213}, {"opcionId": "nacional", "votos": 64}, {"opcionId": "frente-amplio", "votos": 57}], "noPartidarios": {"enBlanco": 0, "anulados": 0, "observados": 0}}, {"geoId": "111", "local": "rivera-L028", "ganadorOpcionId": "colorado", "validos": 306, "porOpcion": [{"opcionId": "colorado", "votos": 190}, {"opcionId": "nacional", "votos": 63}, {"opcionId": "frente-amplio", "votos": 53}], "noPartidarios": {"enBlanco": 0, "anulados": 0, "observados": 0}}, {"geoId": "112", "local": "rivera-L030", "ganadorOpcionId": "colorado", "validos": 339, "porOpcion": [{"opcionId": "colorado", "votos": 213}, {"opcionId": "nacional", "votos": 72}, {"opcionId": "frente-amplio", "votos": 54}], "noPartidarios": {"enBlanco": 0, "anulados": 0, "observados": 0}}, {"geoId": "113", "local": "rivera-L030", "ganadorOpcionId": "colorado", "validos": 322, "porOpcion": [{"opcionId": "colorado", "votos": 232}, {"opcionId": "nacional", "votos": 50}, {"opcionId": "frente-amplio", "votos": 40}], "noPartidarios": {"enBlanco": 0, "anulados": 0, "observados": 0}}, {"geoId": "114", "local": "rivera-L030", "ganadorOpcionId": "colorado", "validos": 316, "porOpcion": [{"opcionId": "colorado", "votos": 219}, {"opcionId": "nacional", "votos": 58}, {"opcionId": "frente-amplio", "votos": 39}], "noPartidarios": {"enBlanco": 0, "anulados": 0, "observados": 0}}, {"geoId": "115", "local": "rivera-L030", "ganadorOpcionId": "colorado", "validos": 315, "porOpcion": [{"opcionId": "colorado", "votos": 186}, {"opcionId": "nacional", "votos": 75}, {"opcionId": "frente-amplio", "votos": 54}], "noPartidarios": {"enBlanco": 0, "anulados": 0, "observados": 0}}, {"geoId": "116", "local": "rivera-L031", "ganadorOpcionId": "colorado", "validos": 329, "porOpcion": [{"opcionId": "colorado", "votos": 214}, {"opcionId": "frente-amplio", "votos": 58}, {"opcionId": "nacional", "votos": 57}], "noPartidarios": {"enBlanco": 0, "anulados": 0, "observados": 0}}, {"geoId": "117", "local": "rivera-L031", "ganadorOpcionId": "colorado", "validos": 312, "porOpcion": [{"opcionId": "colorado", "votos": 201}, {"opcionId": "nacional", "votos": 69}, {"opcionId": "frente-amplio", "votos": 42}], "noPartidarios": {"enBlanco": 0, "anulados": 0, "observados": 0}}, {"geoId": "118", "local": "rivera-L031", "ganadorOpcionId": "colorado", "validos": 329, "porOpcion": [{"opcionId": "colorado", "votos": 226}, {"opcionId": "nacional", "votos": 56}, {"opcionId": "frente-amplio", "votos": 47}], "noPartidarios": {"enBlanco": 0, "anulados": 0, "observados": 0}}, {"geoId": "119", "local": "rivera-L031", "ganadorOpcionId": "colorado", "validos": 314, "porOpcion": [{"opcionId": "colorado", "votos": 203}, {"opcionId": "nacional", "votos": 57}, {"opcionId": "frente-amplio", "votos": 54}], "noPartidarios": {"enBlanco": 0, "anulados": 0, "observados": 0}}, {"geoId": "120", "local": "rivera-L029", "ganadorOpcionId": "colorado", "validos": 325, "porOpcion": [{"opcionId": "colorado", "votos": 202}, {"opcionId": "nacional", "votos": 84}, {"opcionId": "frente-amplio", "votos": 39}], "noPartidarios": {"enBlanco": 0, "anulados": 0, "observados": 0}}, {"geoId": "121", "local": "rivera-L029", "ganadorOpcionId": "colorado", "validos": 317, "porOpcion": [{"opcionId": "colorado", "votos": 194}, {"opcionId": "nacional", "votos": 67}, {"opcionId": "frente-amplio", "votos": 56}], "noPartidarios": {"enBlanco": 0, "anulados": 0, "observados": 0}}, {"geoId": "122", "local": "rivera-L029", "ganadorOpcionId": "colorado", "validos": 308, "porOpcion": [{"opcionId": "colorado", "votos": 202}, {"opcionId": "nacional", "votos": 61}, {"opcionId": "frente-amplio", "votos": 45}], "noPartidarios": {"enBlanco": 0, "anulados": 0, "observados": 0}}, {"geoId": "123", "local": "rivera-L029", "ganadorOpcionId": "colorado", "validos": 316, "porOpcion": [{"opcionId": "colorado", "votos": 196}, {"opcionId": "nacional", "votos": 70}, {"opcionId": "frente-amplio", "votos": 50}], "noPartidarios": {"enBlanco": 0, "anulados": 0, "observados": 0}}, {"geoId": "124", "local": "rivera-L032", "ganadorOpcionId": "colorado", "validos": 345, "porOpcion": [{"opcionId": "colorado", "votos": 219}, {"opcionId": "nacional", "votos": 75}, {"opcionId": "frente-amplio", "votos": 50}, {"opcionId": "asamblea-popular", "votos": 1}], "noPartidarios": {"enBlanco": 0, "anulados": 0, "observados": 0}}, {"geoId": "125", "local": "rivera-L032", "ganadorOpcionId": "colorado", "validos": 331, "porOpcion": [{"opcionId": "colorado", "votos": 213}, {"opcionId": "nacional", "votos": 63}, {"opcionId": "frente-amplio", "votos": 54}, {"opcionId": "asamblea-popular", "votos": 1}], "noPartidarios": {"enBlanco": 0, "anulados": 0, "observados": 0}}, {"geoId": "126", "local": "rivera-L029", "ganadorOpcionId": "colorado", "validos": 196, "porOpcion": [{"opcionId": "colorado", "votos": 123}, {"opcionId": "nacional", "votos": 59}, {"opcionId": "frente-amplio", "votos": 13}, {"opcionId": "asamblea-popular", "votos": 1}], "noPartidarios": {"enBlanco": 0, "anulados": 0, "observados": 0}}, {"geoId": "127", "local": "rivera-L029", "ganadorOpcionId": "colorado", "validos": 187, "porOpcion": [{"opcionId": "colorado", "votos": 96}, {"opcionId": "frente-amplio", "votos": 47}, {"opcionId": "nacional", "votos": 44}], "noPartidarios": {"enBlanco": 0, "anulados": 0, "observados": 0}}, {"geoId": "128", "local": "rivera-L033", "ganadorOpcionId": "colorado", "validos": 318, "porOpcion": [{"opcionId": "colorado", "votos": 181}, {"opcionId": "nacional", "votos": 104}, {"opcionId": "frente-amplio", "votos": 33}], "noPartidarios": {"enBlanco": 0, "anulados": 0, "observados": 0}}, {"geoId": "129", "local": "rivera-L033", "ganadorOpcionId": "colorado", "validos": 325, "porOpcion": [{"opcionId": "colorado", "votos": 212}, {"opcionId": "nacional", "votos": 72}, {"opcionId": "frente-amplio", "votos": 41}], "noPartidarios": {"enBlanco": 0, "anulados": 0, "observados": 0}}, {"geoId": "130", "local": "rivera-L034", "ganadorOpcionId": "colorado", "validos": 321, "porOpcion": [{"opcionId": "colorado", "votos": 184}, {"opcionId": "nacional", "votos": 80}, {"opcionId": "frente-amplio", "votos": 57}], "noPartidarios": {"enBlanco": 0, "anulados": 0, "observados": 0}}, {"geoId": "131", "local": "rivera-L034", "ganadorOpcionId": "colorado", "validos": 323, "porOpcion": [{"opcionId": "colorado", "votos": 194}, {"opcionId": "nacional", "votos": 74}, {"opcionId": "frente-amplio", "votos": 55}], "noPartidarios": {"enBlanco": 0, "anulados": 0, "observados": 0}}, {"geoId": "132", "local": "rivera-L034", "ganadorOpcionId": "colorado", "validos": 306, "porOpcion": [{"opcionId": "colorado", "votos": 186}, {"opcionId": "nacional", "votos": 73}, {"opcionId": "frente-amplio", "votos": 46}, {"opcionId": "asamblea-popular", "votos": 1}], "noPartidarios": {"enBlanco": 0, "anulados": 0, "observados": 0}}, {"geoId": "133", "local": "rivera-L034", "ganadorOpcionId": "colorado", "validos": 309, "porOpcion": [{"opcionId": "colorado", "votos": 208}, {"opcionId": "nacional", "votos": 58}, {"opcionId": "frente-amplio", "votos": 43}], "noPartidarios": {"enBlanco": 0, "anulados": 0, "observados": 0}}, {"geoId": "134", "local": "rivera-L034", "ganadorOpcionId": "colorado", "validos": 325, "porOpcion": [{"opcionId": "colorado", "votos": 202}, {"opcionId": "nacional", "votos": 80}, {"opcionId": "frente-amplio", "votos": 43}], "noPartidarios": {"enBlanco": 0, "anulados": 0, "observados": 0}}, {"geoId": "135", "local": "rivera-L034", "ganadorOpcionId": "colorado", "validos": 326, "porOpcion": [{"opcionId": "colorado", "votos": 188}, {"opcionId": "nacional", "votos": 85}, {"opcionId": "frente-amplio", "votos": 53}], "noPartidarios": {"enBlanco": 0, "anulados": 0, "observados": 0}}, {"geoId": "136", "local": "rivera-L035", "ganadorOpcionId": "colorado", "validos": 319, "porOpcion": [{"opcionId": "colorado", "votos": 199}, {"opcionId": "nacional", "votos": 80}, {"opcionId": "frente-amplio", "votos": 39}, {"opcionId": "asamblea-popular", "votos": 1}], "noPartidarios": {"enBlanco": 0, "anulados": 0, "observados": 0}}, {"geoId": "137", "local": "rivera-L035", "ganadorOpcionId": "colorado", "validos": 294, "porOpcion": [{"opcionId": "colorado", "votos": 171}, {"opcionId": "nacional", "votos": 62}, {"opcionId": "frente-amplio", "votos": 60}, {"opcionId": "asamblea-popular", "votos": 1}], "noPartidarios": {"enBlanco": 0, "anulados": 0, "observados": 0}}, {"geoId": "138", "local": "rivera-L035", "ganadorOpcionId": "colorado", "validos": 300, "porOpcion": [{"opcionId": "colorado", "votos": 161}, {"opcionId": "nacional", "votos": 73}, {"opcionId": "frente-amplio", "votos": 66}], "noPartidarios": {"enBlanco": 0, "anulados": 0, "observados": 0}}, {"geoId": "139", "local": "rivera-L035", "ganadorOpcionId": "colorado", "validos": 299, "porOpcion": [{"opcionId": "colorado", "votos": 171}, {"opcionId": "nacional", "votos": 91}, {"opcionId": "frente-amplio", "votos": 37}], "noPartidarios": {"enBlanco": 0, "anulados": 0, "observados": 0}}, {"geoId": "140", "local": "rivera-L035", "ganadorOpcionId": "colorado", "validos": 303, "porOpcion": [{"opcionId": "colorado", "votos": 176}, {"opcionId": "nacional", "votos": 70}, {"opcionId": "frente-amplio", "votos": 57}], "noPartidarios": {"enBlanco": 0, "anulados": 0, "observados": 0}}, {"geoId": "141", "local": "rivera-L035", "ganadorOpcionId": "colorado", "validos": 329, "porOpcion": [{"opcionId": "colorado", "votos": 181}, {"opcionId": "nacional", "votos": 96}, {"opcionId": "frente-amplio", "votos": 50}, {"opcionId": "asamblea-popular", "votos": 2}], "noPartidarios": {"enBlanco": 0, "anulados": 0, "observados": 0}}, {"geoId": "142", "local": "rivera-L036", "ganadorOpcionId": "colorado", "validos": 336, "porOpcion": [{"opcionId": "colorado", "votos": 188}, {"opcionId": "nacional", "votos": 77}, {"opcionId": "frente-amplio", "votos": 71}], "noPartidarios": {"enBlanco": 0, "anulados": 0, "observados": 0}}, {"geoId": "143", "local": "rivera-L037", "ganadorOpcionId": "colorado", "validos": 298, "porOpcion": [{"opcionId": "colorado", "votos": 185}, {"opcionId": "nacional", "votos": 84}, {"opcionId": "frente-amplio", "votos": 29}], "noPartidarios": {"enBlanco": 0, "anulados": 0, "observados": 0}}, {"geoId": "144", "local": "rivera-L037", "ganadorOpcionId": "colorado", "validos": 332, "porOpcion": [{"opcionId": "colorado", "votos": 231}, {"opcionId": "nacional", "votos": 66}, {"opcionId": "frente-amplio", "votos": 35}], "noPartidarios": {"enBlanco": 0, "anulados": 0, "observados": 0}}, {"geoId": "145", "local": "rivera-L037", "ganadorOpcionId": "colorado", "validos": 325, "porOpcion": [{"opcionId": "colorado", "votos": 207}, {"opcionId": "nacional", "votos": 90}, {"opcionId": "frente-amplio", "votos": 27}, {"opcionId": "asamblea-popular", "votos": 1}], "noPartidarios": {"enBlanco": 0, "anulados": 0, "observados": 0}}, {"geoId": "146", "local": "rivera-L037", "ganadorOpcionId": "colorado", "validos": 310, "porOpcion": [{"opcionId": "colorado", "votos": 188}, {"opcionId": "nacional", "votos": 78}, {"opcionId": "frente-amplio", "votos": 44}], "noPartidarios": {"enBlanco": 0, "anulados": 0, "observados": 0}}, {"geoId": "147", "local": "rivera-L038", "ganadorOpcionId": "colorado", "validos": 314, "porOpcion": [{"opcionId": "colorado", "votos": 167}, {"opcionId": "frente-amplio", "votos": 74}, {"opcionId": "nacional", "votos": 73}], "noPartidarios": {"enBlanco": 0, "anulados": 0, "observados": 0}}, {"geoId": "148", "local": "rivera-L038", "ganadorOpcionId": "colorado", "validos": 318, "porOpcion": [{"opcionId": "colorado", "votos": 186}, {"opcionId": "nacional", "votos": 68}, {"opcionId": "frente-amplio", "votos": 64}], "noPartidarios": {"enBlanco": 0, "anulados": 0, "observados": 0}}, {"geoId": "149", "local": "rivera-L038", "ganadorOpcionId": "colorado", "validos": 318, "porOpcion": [{"opcionId": "colorado", "votos": 196}, {"opcionId": "nacional", "votos": 61}, {"opcionId": "frente-amplio", "votos": 60}, {"opcionId": "asamblea-popular", "votos": 1}], "noPartidarios": {"enBlanco": 0, "anulados": 0, "observados": 0}}, {"geoId": "150", "local": "rivera-L039", "ganadorOpcionId": "colorado", "validos": 316, "porOpcion": [{"opcionId": "colorado", "votos": 216}, {"opcionId": "nacional", "votos": 52}, {"opcionId": "frente-amplio", "votos": 46}, {"opcionId": "asamblea-popular", "votos": 2}], "noPartidarios": {"enBlanco": 0, "anulados": 0, "observados": 0}}, {"geoId": "151", "local": "rivera-L039", "ganadorOpcionId": "colorado", "validos": 308, "porOpcion": [{"opcionId": "colorado", "votos": 207}, {"opcionId": "frente-amplio", "votos": 53}, {"opcionId": "nacional", "votos": 47}, {"opcionId": "asamblea-popular", "votos": 1}], "noPartidarios": {"enBlanco": 0, "anulados": 0, "observados": 0}}, {"geoId": "152", "local": "rivera-L040", "ganadorOpcionId": "colorado", "validos": 318, "porOpcion": [{"opcionId": "colorado", "votos": 214}, {"opcionId": "nacional", "votos": 55}, {"opcionId": "frente-amplio", "votos": 48}, {"opcionId": "asamblea-popular", "votos": 1}], "noPartidarios": {"enBlanco": 0, "anulados": 0, "observados": 0}}, {"geoId": "153", "local": "rivera-L040", "ganadorOpcionId": "colorado", "validos": 303, "porOpcion": [{"opcionId": "colorado", "votos": 170}, {"opcionId": "nacional", "votos": 88}, {"opcionId": "frente-amplio", "votos": 44}, {"opcionId": "asamblea-popular", "votos": 1}], "noPartidarios": {"enBlanco": 0, "anulados": 0, "observados": 0}}, {"geoId": "154", "local": "rivera-L041", "ganadorOpcionId": "colorado", "validos": 318, "porOpcion": [{"opcionId": "colorado", "votos": 198}, {"opcionId": "nacional", "votos": 67}, {"opcionId": "frente-amplio", "votos": 53}], "noPartidarios": {"enBlanco": 0, "anulados": 0, "observados": 0}}, {"geoId": "155", "local": "rivera-L041", "ganadorOpcionId": "colorado", "validos": 320, "porOpcion": [{"opcionId": "colorado", "votos": 188}, {"opcionId": "nacional", "votos": 75}, {"opcionId": "frente-amplio", "votos": 57}], "noPartidarios": {"enBlanco": 0, "anulados": 0, "observados": 0}}, {"geoId": "156", "local": "rivera-L042", "ganadorOpcionId": "colorado", "validos": 327, "porOpcion": [{"opcionId": "colorado", "votos": 192}, {"opcionId": "nacional", "votos": 71}, {"opcionId": "frente-amplio", "votos": 64}], "noPartidarios": {"enBlanco": 0, "anulados": 0, "observados": 0}}, {"geoId": "157", "local": "rivera-L043", "ganadorOpcionId": "colorado", "validos": 323, "porOpcion": [{"opcionId": "colorado", "votos": 181}, {"opcionId": "nacional", "votos": 84}, {"opcionId": "frente-amplio", "votos": 57}, {"opcionId": "asamblea-popular", "votos": 1}], "noPartidarios": {"enBlanco": 0, "anulados": 0, "observados": 0}}, {"geoId": "158", "local": "rivera-L043", "ganadorOpcionId": "colorado", "validos": 304, "porOpcion": [{"opcionId": "colorado", "votos": 171}, {"opcionId": "nacional", "votos": 79}, {"opcionId": "frente-amplio", "votos": 54}], "noPartidarios": {"enBlanco": 0, "anulados": 0, "observados": 0}}, {"geoId": "159", "local": "rivera-L043", "ganadorOpcionId": "colorado", "validos": 297, "porOpcion": [{"opcionId": "colorado", "votos": 184}, {"opcionId": "nacional", "votos": 62}, {"opcionId": "frente-amplio", "votos": 51}], "noPartidarios": {"enBlanco": 0, "anulados": 0, "observados": 0}}, {"geoId": "160", "local": "rivera-L044", "ganadorOpcionId": "colorado", "validos": 325, "porOpcion": [{"opcionId": "colorado", "votos": 200}, {"opcionId": "frente-amplio", "votos": 67}, {"opcionId": "nacional", "votos": 57}, {"opcionId": "asamblea-popular", "votos": 1}], "noPartidarios": {"enBlanco": 0, "anulados": 0, "observados": 0}}, {"geoId": "161", "local": "rivera-L044", "ganadorOpcionId": "colorado", "validos": 318, "porOpcion": [{"opcionId": "colorado", "votos": 181}, {"opcionId": "nacional", "votos": 84}, {"opcionId": "frente-amplio", "votos": 53}], "noPartidarios": {"enBlanco": 0, "anulados": 0, "observados": 0}}, {"geoId": "162", "local": "rivera-L044", "ganadorOpcionId": "colorado", "validos": 301, "porOpcion": [{"opcionId": "colorado", "votos": 182}, {"opcionId": "nacional", "votos": 65}, {"opcionId": "frente-amplio", "votos": 54}], "noPartidarios": {"enBlanco": 0, "anulados": 0, "observados": 0}}, {"geoId": "163", "local": "rivera-L044", "ganadorOpcionId": "colorado", "validos": 298, "porOpcion": [{"opcionId": "colorado", "votos": 167}, {"opcionId": "nacional", "votos": 73}, {"opcionId": "frente-amplio", "votos": 58}], "noPartidarios": {"enBlanco": 0, "anulados": 0, "observados": 0}}, {"geoId": "164", "local": "rivera-L044", "ganadorOpcionId": "colorado", "validos": 284, "porOpcion": [{"opcionId": "colorado", "votos": 158}, {"opcionId": "nacional", "votos": 80}, {"opcionId": "frente-amplio", "votos": 46}], "noPartidarios": {"enBlanco": 0, "anulados": 0, "observados": 0}}, {"geoId": "165", "local": "rivera-L045", "ganadorOpcionId": "colorado", "validos": 312, "porOpcion": [{"opcionId": "colorado", "votos": 175}, {"opcionId": "nacional", "votos": 74}, {"opcionId": "frente-amplio", "votos": 62}, {"opcionId": "asamblea-popular", "votos": 1}], "noPartidarios": {"enBlanco": 0, "anulados": 0, "observados": 0}}, {"geoId": "166", "local": "rivera-L045", "ganadorOpcionId": "colorado", "validos": 316, "porOpcion": [{"opcionId": "colorado", "votos": 207}, {"opcionId": "nacional", "votos": 68}, {"opcionId": "frente-amplio", "votos": 41}], "noPartidarios": {"enBlanco": 0, "anulados": 0, "observados": 0}}, {"geoId": "167", "local": "rivera-L046", "ganadorOpcionId": "colorado", "validos": 306, "porOpcion": [{"opcionId": "colorado", "votos": 175}, {"opcionId": "frente-amplio", "votos": 67}, {"opcionId": "nacional", "votos": 64}], "noPartidarios": {"enBlanco": 0, "anulados": 0, "observados": 0}}, {"geoId": "168", "local": "rivera-L047", "ganadorOpcionId": "colorado", "validos": 322, "porOpcion": [{"opcionId": "colorado", "votos": 196}, {"opcionId": "nacional", "votos": 84}, {"opcionId": "frente-amplio", "votos": 41}, {"opcionId": "asamblea-popular", "votos": 1}], "noPartidarios": {"enBlanco": 0, "anulados": 0, "observados": 0}}, {"geoId": "169", "local": "rivera-L047", "ganadorOpcionId": "colorado", "validos": 320, "porOpcion": [{"opcionId": "colorado", "votos": 187}, {"opcionId": "nacional", "votos": 72}, {"opcionId": "frente-amplio", "votos": 61}], "noPartidarios": {"enBlanco": 0, "anulados": 0, "observados": 0}}, {"geoId": "170", "local": "rivera-L047", "ganadorOpcionId": "colorado", "validos": 310, "porOpcion": [{"opcionId": "colorado", "votos": 170}, {"opcionId": "nacional", "votos": 99}, {"opcionId": "frente-amplio", "votos": 41}], "noPartidarios": {"enBlanco": 0, "anulados": 0, "observados": 0}}, {"geoId": "171", "local": "rivera-L047", "ganadorOpcionId": "colorado", "validos": 309, "porOpcion": [{"opcionId": "colorado", "votos": 184}, {"opcionId": "nacional", "votos": 71}, {"opcionId": "frente-amplio", "votos": 53}, {"opcionId": "asamblea-popular", "votos": 1}], "noPartidarios": {"enBlanco": 0, "anulados": 0, "observados": 0}}, {"geoId": "172", "local": "rivera-L048", "ganadorOpcionId": "colorado", "validos": 306, "porOpcion": [{"opcionId": "colorado", "votos": 176}, {"opcionId": "nacional", "votos": 80}, {"opcionId": "frente-amplio", "votos": 48}, {"opcionId": "asamblea-popular", "votos": 2}], "noPartidarios": {"enBlanco": 0, "anulados": 0, "observados": 0}}, {"geoId": "173", "local": "rivera-L048", "ganadorOpcionId": "colorado", "validos": 303, "porOpcion": [{"opcionId": "colorado", "votos": 170}, {"opcionId": "nacional", "votos": 75}, {"opcionId": "frente-amplio", "votos": 58}], "noPartidarios": {"enBlanco": 0, "anulados": 0, "observados": 0}}, {"geoId": "174", "local": "rivera-L048", "ganadorOpcionId": "colorado", "validos": 288, "porOpcion": [{"opcionId": "colorado", "votos": 163}, {"opcionId": "nacional", "votos": 76}, {"opcionId": "frente-amplio", "votos": 49}], "noPartidarios": {"enBlanco": 0, "anulados": 0, "observados": 0}}, {"geoId": "175", "local": "rivera-L049", "ganadorOpcionId": "colorado", "validos": 288, "porOpcion": [{"opcionId": "colorado", "votos": 168}, {"opcionId": "nacional", "votos": 80}, {"opcionId": "frente-amplio", "votos": 40}], "noPartidarios": {"enBlanco": 0, "anulados": 0, "observados": 0}}, {"geoId": "176", "local": "rivera-L049", "ganadorOpcionId": "colorado", "validos": 308, "porOpcion": [{"opcionId": "colorado", "votos": 187}, {"opcionId": "nacional", "votos": 75}, {"opcionId": "frente-amplio", "votos": 46}], "noPartidarios": {"enBlanco": 0, "anulados": 0, "observados": 0}}, {"geoId": "177", "local": "rivera-L049", "ganadorOpcionId": "colorado", "validos": 307, "porOpcion": [{"opcionId": "colorado", "votos": 183}, {"opcionId": "frente-amplio", "votos": 67}, {"opcionId": "nacional", "votos": 56}, {"opcionId": "asamblea-popular", "votos": 1}], "noPartidarios": {"enBlanco": 0, "anulados": 0, "observados": 0}}, {"geoId": "178", "local": "rivera-L049", "ganadorOpcionId": "colorado", "validos": 323, "porOpcion": [{"opcionId": "colorado", "votos": 188}, {"opcionId": "nacional", "votos": 78}, {"opcionId": "frente-amplio", "votos": 57}], "noPartidarios": {"enBlanco": 0, "anulados": 0, "observados": 0}}, {"geoId": "179", "local": "rivera-L050", "ganadorOpcionId": "colorado", "validos": 319, "porOpcion": [{"opcionId": "colorado", "votos": 180}, {"opcionId": "nacional", "votos": 77}, {"opcionId": "frente-amplio", "votos": 61}, {"opcionId": "asamblea-popular", "votos": 1}], "noPartidarios": {"enBlanco": 0, "anulados": 0, "observados": 0}}, {"geoId": "180", "local": "rivera-L051", "ganadorOpcionId": "colorado", "validos": 122, "porOpcion": [{"opcionId": "colorado", "votos": 78}, {"opcionId": "nacional", "votos": 36}, {"opcionId": "frente-amplio", "votos": 8}], "noPartidarios": {"enBlanco": 0, "anulados": 0, "observados": 0}}, {"geoId": "181", "local": "rivera-L052", "ganadorOpcionId": "colorado", "validos": 63, "porOpcion": [{"opcionId": "colorado", "votos": 27}, {"opcionId": "nacional", "votos": 25}, {"opcionId": "frente-amplio", "votos": 11}], "noPartidarios": {"enBlanco": 0, "anulados": 0, "observados": 0}}, {"geoId": "182", "local": "rivera-L053", "ganadorOpcionId": "colorado", "validos": 214, "porOpcion": [{"opcionId": "colorado", "votos": 164}, {"opcionId": "nacional", "votos": 42}, {"opcionId": "frente-amplio", "votos": 8}], "noPartidarios": {"enBlanco": 0, "anulados": 0, "observados": 0}}, {"geoId": "183", "local": "rivera-L053", "ganadorOpcionId": "colorado", "validos": 230, "porOpcion": [{"opcionId": "colorado", "votos": 181}, {"opcionId": "nacional", "votos": 34}, {"opcionId": "frente-amplio", "votos": 15}], "noPartidarios": {"enBlanco": 0, "anulados": 0, "observados": 0}}, {"geoId": "184", "local": "rivera-L053", "ganadorOpcionId": "colorado", "validos": 227, "porOpcion": [{"opcionId": "colorado", "votos": 188}, {"opcionId": "nacional", "votos": 22}, {"opcionId": "frente-amplio", "votos": 17}], "noPartidarios": {"enBlanco": 0, "anulados": 0, "observados": 0}}, {"geoId": "185", "local": "rivera-L053", "ganadorOpcionId": "colorado", "validos": 232, "porOpcion": [{"opcionId": "colorado", "votos": 186}, {"opcionId": "nacional", "votos": 32}, {"opcionId": "frente-amplio", "votos": 14}], "noPartidarios": {"enBlanco": 0, "anulados": 0, "observados": 0}}, {"geoId": "186", "local": "rivera-L054", "ganadorOpcionId": "colorado", "validos": 208, "porOpcion": [{"opcionId": "colorado", "votos": 156}, {"opcionId": "frente-amplio", "votos": 26}, {"opcionId": "nacional", "votos": 26}], "noPartidarios": {"enBlanco": 0, "anulados": 0, "observados": 0}}, {"geoId": "187", "local": "rivera-L054", "ganadorOpcionId": "colorado", "validos": 204, "porOpcion": [{"opcionId": "colorado", "votos": 169}, {"opcionId": "nacional", "votos": 25}, {"opcionId": "frente-amplio", "votos": 10}], "noPartidarios": {"enBlanco": 0, "anulados": 0, "observados": 0}}, {"geoId": "188", "local": "rivera-L054", "ganadorOpcionId": "colorado", "validos": 208, "porOpcion": [{"opcionId": "colorado", "votos": 173}, {"opcionId": "nacional", "votos": 23}, {"opcionId": "frente-amplio", "votos": 12}], "noPartidarios": {"enBlanco": 0, "anulados": 0, "observados": 0}}, {"geoId": "189", "local": "rivera-L054", "ganadorOpcionId": "colorado", "validos": 195, "porOpcion": [{"opcionId": "colorado", "votos": 156}, {"opcionId": "nacional", "votos": 24}, {"opcionId": "frente-amplio", "votos": 15}], "noPartidarios": {"enBlanco": 0, "anulados": 0, "observados": 0}}, {"geoId": "190", "local": "rivera-L055", "ganadorOpcionId": "colorado", "validos": 187, "porOpcion": [{"opcionId": "colorado", "votos": 149}, {"opcionId": "nacional", "votos": 27}, {"opcionId": "frente-amplio", "votos": 11}], "noPartidarios": {"enBlanco": 0, "anulados": 0, "observados": 0}}, {"geoId": "191", "local": "rivera-L055", "ganadorOpcionId": "colorado", "validos": 165, "porOpcion": [{"opcionId": "colorado", "votos": 138}, {"opcionId": "nacional", "votos": 19}, {"opcionId": "frente-amplio", "votos": 8}], "noPartidarios": {"enBlanco": 0, "anulados": 0, "observados": 0}}, {"geoId": "192", "local": "rivera-L055", "ganadorOpcionId": "colorado", "validos": 176, "porOpcion": [{"opcionId": "colorado", "votos": 143}, {"opcionId": "nacional", "votos": 21}, {"opcionId": "frente-amplio", "votos": 12}], "noPartidarios": {"enBlanco": 0, "anulados": 0, "observados": 0}}, {"geoId": "193", "local": "rivera-L055", "ganadorOpcionId": "colorado", "validos": 177, "porOpcion": [{"opcionId": "colorado", "votos": 139}, {"opcionId": "nacional", "votos": 22}, {"opcionId": "frente-amplio", "votos": 16}], "noPartidarios": {"enBlanco": 0, "anulados": 0, "observados": 0}}, {"geoId": "194", "local": "rivera-L056", "ganadorOpcionId": "colorado", "validos": 176, "porOpcion": [{"opcionId": "colorado", "votos": 133}, {"opcionId": "nacional", "votos": 26}, {"opcionId": "frente-amplio", "votos": 17}], "noPartidarios": {"enBlanco": 0, "anulados": 0, "observados": 0}}, {"geoId": "195", "local": "rivera-L056", "ganadorOpcionId": "colorado", "validos": 170, "porOpcion": [{"opcionId": "colorado", "votos": 138}, {"opcionId": "nacional", "votos": 28}, {"opcionId": "frente-amplio", "votos": 4}], "noPartidarios": {"enBlanco": 0, "anulados": 0, "observados": 0}}, {"geoId": "196", "local": "rivera-L056", "ganadorOpcionId": "colorado", "validos": 183, "porOpcion": [{"opcionId": "colorado", "votos": 148}, {"opcionId": "nacional", "votos": 26}, {"opcionId": "frente-amplio", "votos": 9}], "noPartidarios": {"enBlanco": 0, "anulados": 0, "observados": 0}}, {"geoId": "197", "local": "rivera-L056", "ganadorOpcionId": "colorado", "validos": 171, "porOpcion": [{"opcionId": "colorado", "votos": 137}, {"opcionId": "nacional", "votos": 24}, {"opcionId": "frente-amplio", "votos": 10}], "noPartidarios": {"enBlanco": 0, "anulados": 0, "observados": 0}}, {"geoId": "198", "local": "rivera-L056", "ganadorOpcionId": "colorado", "validos": 200, "porOpcion": [{"opcionId": "colorado", "votos": 162}, {"opcionId": "nacional", "votos": 30}, {"opcionId": "frente-amplio", "votos": 8}], "noPartidarios": {"enBlanco": 0, "anulados": 0, "observados": 0}}, {"geoId": "199", "local": "rivera-L056", "ganadorOpcionId": "colorado", "validos": 191, "porOpcion": [{"opcionId": "colorado", "votos": 158}, {"opcionId": "nacional", "votos": 22}, {"opcionId": "frente-amplio", "votos": 11}], "noPartidarios": {"enBlanco": 0, "anulados": 0, "observados": 0}}, {"geoId": "200", "local": "rivera-L057", "ganadorOpcionId": "colorado", "validos": 179, "porOpcion": [{"opcionId": "colorado", "votos": 140}, {"opcionId": "nacional", "votos": 26}, {"opcionId": "frente-amplio", "votos": 13}], "noPartidarios": {"enBlanco": 0, "anulados": 0, "observados": 0}}, {"geoId": "201", "local": "rivera-L057", "ganadorOpcionId": "colorado", "validos": 188, "porOpcion": [{"opcionId": "colorado", "votos": 150}, {"opcionId": "nacional", "votos": 29}, {"opcionId": "frente-amplio", "votos": 9}], "noPartidarios": {"enBlanco": 0, "anulados": 0, "observados": 0}}, {"geoId": "202", "local": "rivera-L057", "ganadorOpcionId": "colorado", "validos": 182, "porOpcion": [{"opcionId": "colorado", "votos": 153}, {"opcionId": "nacional", "votos": 16}, {"opcionId": "frente-amplio", "votos": 13}], "noPartidarios": {"enBlanco": 0, "anulados": 0, "observados": 0}}, {"geoId": "203", "local": "rivera-L057", "ganadorOpcionId": "colorado", "validos": 203, "porOpcion": [{"opcionId": "colorado", "votos": 161}, {"opcionId": "nacional", "votos": 31}, {"opcionId": "frente-amplio", "votos": 11}], "noPartidarios": {"enBlanco": 0, "anulados": 0, "observados": 0}}, {"geoId": "204", "local": "rivera-L058", "ganadorOpcionId": "colorado", "validos": 124, "porOpcion": [{"opcionId": "colorado", "votos": 102}, {"opcionId": "nacional", "votos": 19}, {"opcionId": "frente-amplio", "votos": 3}], "noPartidarios": {"enBlanco": 0, "anulados": 0, "observados": 0}}, {"geoId": "205", "local": "rivera-L059", "ganadorOpcionId": "colorado", "validos": 97, "porOpcion": [{"opcionId": "colorado", "votos": 54}, {"opcionId": "nacional", "votos": 39}, {"opcionId": "frente-amplio", "votos": 4}], "noPartidarios": {"enBlanco": 0, "anulados": 0, "observados": 0}}, {"geoId": "206", "local": "rivera-L060", "ganadorOpcionId": "colorado", "validos": 191, "porOpcion": [{"opcionId": "colorado", "votos": 116}, {"opcionId": "nacional", "votos": 62}, {"opcionId": "frente-amplio", "votos": 13}], "noPartidarios": {"enBlanco": 0, "anulados": 0, "observados": 0}}, {"geoId": "207", "local": "rivera-L060", "ganadorOpcionId": "colorado", "validos": 177, "porOpcion": [{"opcionId": "colorado", "votos": 115}, {"opcionId": "nacional", "votos": 50}, {"opcionId": "frente-amplio", "votos": 11}, {"opcionId": "asamblea-popular", "votos": 1}], "noPartidarios": {"enBlanco": 0, "anulados": 0, "observados": 0}}, {"geoId": "208", "local": "rivera-L061", "ganadorOpcionId": "colorado", "validos": 169, "porOpcion": [{"opcionId": "colorado", "votos": 110}, {"opcionId": "frente-amplio", "votos": 37}, {"opcionId": "nacional", "votos": 22}], "noPartidarios": {"enBlanco": 0, "anulados": 0, "observados": 0}}, {"geoId": "209", "local": "rivera-L062", "ganadorOpcionId": "colorado", "validos": 73, "porOpcion": [{"opcionId": "colorado", "votos": 36}, {"opcionId": "nacional", "votos": 33}, {"opcionId": "frente-amplio", "votos": 4}], "noPartidarios": {"enBlanco": 0, "anulados": 0, "observados": 0}}, {"geoId": "210", "local": "rivera-L063", "ganadorOpcionId": "colorado", "validos": 211, "porOpcion": [{"opcionId": "colorado", "votos": 152}, {"opcionId": "nacional", "votos": 41}, {"opcionId": "frente-amplio", "votos": 18}], "noPartidarios": {"enBlanco": 0, "anulados": 0, "observados": 0}}, {"geoId": "211", "local": "rivera-L063", "ganadorOpcionId": "colorado", "validos": 242, "porOpcion": [{"opcionId": "colorado", "votos": 197}, {"opcionId": "nacional", "votos": 31}, {"opcionId": "frente-amplio", "votos": 14}], "noPartidarios": {"enBlanco": 0, "anulados": 0, "observados": 0}}, {"geoId": "212", "local": "rivera-L063", "ganadorOpcionId": "colorado", "validos": 216, "porOpcion": [{"opcionId": "colorado", "votos": 166}, {"opcionId": "nacional", "votos": 34}, {"opcionId": "frente-amplio", "votos": 16}], "noPartidarios": {"enBlanco": 0, "anulados": 0, "observados": 0}}, {"geoId": "213", "local": "rivera-L064", "ganadorOpcionId": "colorado", "validos": 208, "porOpcion": [{"opcionId": "colorado", "votos": 164}, {"opcionId": "nacional", "votos": 27}, {"opcionId": "frente-amplio", "votos": 17}], "noPartidarios": {"enBlanco": 0, "anulados": 0, "observados": 0}}, {"geoId": "214", "local": "rivera-L064", "ganadorOpcionId": "colorado", "validos": 200, "porOpcion": [{"opcionId": "colorado", "votos": 153}, {"opcionId": "nacional", "votos": 28}, {"opcionId": "frente-amplio", "votos": 19}], "noPartidarios": {"enBlanco": 0, "anulados": 0, "observados": 0}}, {"geoId": "215", "local": "rivera-L064", "ganadorOpcionId": "colorado", "validos": 203, "porOpcion": [{"opcionId": "colorado", "votos": 162}, {"opcionId": "nacional", "votos": 30}, {"opcionId": "frente-amplio", "votos": 11}], "noPartidarios": {"enBlanco": 0, "anulados": 0, "observados": 0}}, {"geoId": "216", "local": "rivera-L064", "ganadorOpcionId": "colorado", "validos": 202, "porOpcion": [{"opcionId": "colorado", "votos": 172}, {"opcionId": "frente-amplio", "votos": 17}, {"opcionId": "nacional", "votos": 13}], "noPartidarios": {"enBlanco": 0, "anulados": 0, "observados": 0}}, {"geoId": "217", "local": "rivera-L064", "ganadorOpcionId": "colorado", "validos": 195, "porOpcion": [{"opcionId": "colorado", "votos": 174}, {"opcionId": "nacional", "votos": 15}, {"opcionId": "frente-amplio", "votos": 6}], "noPartidarios": {"enBlanco": 0, "anulados": 0, "observados": 0}}, {"geoId": "218", "local": "rivera-L065", "ganadorOpcionId": "colorado", "validos": 199, "porOpcion": [{"opcionId": "colorado", "votos": 174}, {"opcionId": "nacional", "votos": 20}, {"opcionId": "frente-amplio", "votos": 5}], "noPartidarios": {"enBlanco": 0, "anulados": 0, "observados": 0}}, {"geoId": "219", "local": "rivera-L065", "ganadorOpcionId": "colorado", "validos": 210, "porOpcion": [{"opcionId": "colorado", "votos": 179}, {"opcionId": "nacional", "votos": 19}, {"opcionId": "frente-amplio", "votos": 12}], "noPartidarios": {"enBlanco": 0, "anulados": 0, "observados": 0}}, {"geoId": "220", "local": "rivera-L065", "ganadorOpcionId": "colorado", "validos": 202, "porOpcion": [{"opcionId": "colorado", "votos": 176}, {"opcionId": "frente-amplio", "votos": 13}, {"opcionId": "nacional", "votos": 13}], "noPartidarios": {"enBlanco": 0, "anulados": 0, "observados": 0}}, {"geoId": "221", "local": "rivera-L066", "ganadorOpcionId": "colorado", "validos": 129, "porOpcion": [{"opcionId": "colorado", "votos": 99}, {"opcionId": "nacional", "votos": 26}, {"opcionId": "frente-amplio", "votos": 4}], "noPartidarios": {"enBlanco": 0, "anulados": 0, "observados": 0}}, {"geoId": "222", "local": "rivera-L067", "ganadorOpcionId": "colorado", "validos": 159, "porOpcion": [{"opcionId": "colorado", "votos": 123}, {"opcionId": "nacional", "votos": 31}, {"opcionId": "frente-amplio", "votos": 4}, {"opcionId": "asamblea-popular", "votos": 1}], "noPartidarios": {"enBlanco": 0, "anulados": 0, "observados": 0}}, {"geoId": "223", "local": "rivera-L067", "ganadorOpcionId": "colorado", "validos": 153, "porOpcion": [{"opcionId": "colorado", "votos": 115}, {"opcionId": "nacional", "votos": 28}, {"opcionId": "frente-amplio", "votos": 10}], "noPartidarios": {"enBlanco": 0, "anulados": 0, "observados": 0}}, {"geoId": "224", "local": "rivera-L068", "ganadorOpcionId": "colorado", "validos": 36, "porOpcion": [{"opcionId": "colorado", "votos": 20}, {"opcionId": "nacional", "votos": 12}, {"opcionId": "frente-amplio", "votos": 4}], "noPartidarios": {"enBlanco": 0, "anulados": 0, "observados": 0}}, {"geoId": "225", "local": "rivera-L069", "ganadorOpcionId": "colorado", "validos": 112, "porOpcion": [{"opcionId": "colorado", "votos": 75}, {"opcionId": "frente-amplio", "votos": 22}, {"opcionId": "nacional", "votos": 15}], "noPartidarios": {"enBlanco": 0, "anulados": 0, "observados": 0}}, {"geoId": "226", "local": "rivera-L070", "ganadorOpcionId": "colorado", "validos": 113, "porOpcion": [{"opcionId": "colorado", "votos": 82}, {"opcionId": "nacional", "votos": 16}, {"opcionId": "frente-amplio", "votos": 15}], "noPartidarios": {"enBlanco": 0, "anulados": 0, "observados": 0}}, {"geoId": "227", "local": "rivera-L071", "ganadorOpcionId": "colorado", "validos": 116, "porOpcion": [{"opcionId": "colorado", "votos": 69}, {"opcionId": "nacional", "votos": 40}, {"opcionId": "frente-amplio", "votos": 7}], "noPartidarios": {"enBlanco": 0, "anulados": 0, "observados": 0}}, {"geoId": "228", "local": "rivera-L072", "ganadorOpcionId": "colorado", "validos": 149, "porOpcion": [{"opcionId": "colorado", "votos": 92}, {"opcionId": "nacional", "votos": 30}, {"opcionId": "frente-amplio", "votos": 27}], "noPartidarios": {"enBlanco": 0, "anulados": 0, "observados": 0}}, {"geoId": "229", "local": "rivera-L072", "ganadorOpcionId": "colorado", "validos": 151, "porOpcion": [{"opcionId": "colorado", "votos": 102}, {"opcionId": "frente-amplio", "votos": 31}, {"opcionId": "nacional", "votos": 18}], "noPartidarios": {"enBlanco": 0, "anulados": 0, "observados": 0}}, {"geoId": "230", "local": "rivera-L071", "ganadorOpcionId": "colorado", "validos": 24, "porOpcion": [{"opcionId": "colorado", "votos": 19}, {"opcionId": "nacional", "votos": 4}, {"opcionId": "frente-amplio", "votos": 1}], "noPartidarios": {"enBlanco": 0, "anulados": 0, "observados": 0}}, {"geoId": "231", "local": "rivera-L073", "ganadorOpcionId": "colorado", "validos": 11, "porOpcion": [{"opcionId": "colorado", "votos": 10}, {"opcionId": "nacional", "votos": 1}], "noPartidarios": {"enBlanco": 0, "anulados": 0, "observados": 0}}, {"geoId": "232", "local": "rivera-L074", "ganadorOpcionId": "colorado", "validos": 129, "porOpcion": [{"opcionId": "colorado", "votos": 82}, {"opcionId": "nacional", "votos": 45}, {"opcionId": "frente-amplio", "votos": 2}], "noPartidarios": {"enBlanco": 0, "anulados": 0, "observados": 0}}, {"geoId": "233", "local": "rivera-L075", "ganadorOpcionId": "colorado", "validos": 92, "porOpcion": [{"opcionId": "colorado", "votos": 46}, {"opcionId": "nacional", "votos": 29}, {"opcionId": "frente-amplio", "votos": 17}], "noPartidarios": {"enBlanco": 0, "anulados": 0, "observados": 0}}, {"geoId": "234", "local": "rivera-L075", "ganadorOpcionId": "colorado", "validos": 100, "porOpcion": [{"opcionId": "colorado", "votos": 43}, {"opcionId": "nacional", "votos": 30}, {"opcionId": "frente-amplio", "votos": 27}], "noPartidarios": {"enBlanco": 0, "anulados": 0, "observados": 0}}, {"geoId": "235", "local": "rivera-L076", "ganadorOpcionId": "colorado", "validos": 102, "porOpcion": [{"opcionId": "colorado", "votos": 51}, {"opcionId": "nacional", "votos": 34}, {"opcionId": "frente-amplio", "votos": 17}], "noPartidarios": {"enBlanco": 0, "anulados": 0, "observados": 0}}, {"geoId": "236", "local": "rivera-L076", "ganadorOpcionId": "colorado", "validos": 105, "porOpcion": [{"opcionId": "colorado", "votos": 58}, {"opcionId": "nacional", "votos": 36}, {"opcionId": "frente-amplio", "votos": 11}], "noPartidarios": {"enBlanco": 0, "anulados": 0, "observados": 0}}, {"geoId": "237", "local": "rivera-L077", "ganadorOpcionId": "colorado", "validos": 70, "porOpcion": [{"opcionId": "colorado", "votos": 39}, {"opcionId": "nacional", "votos": 16}, {"opcionId": "frente-amplio", "votos": 15}], "noPartidarios": {"enBlanco": 0, "anulados": 0, "observados": 0}}, {"geoId": "238", "local": "rivera-L078", "ganadorOpcionId": "nacional", "validos": 75, "porOpcion": [{"opcionId": "nacional", "votos": 34}, {"opcionId": "colorado", "votos": 24}, {"opcionId": "frente-amplio", "votos": 16}, {"opcionId": "asamblea-popular", "votos": 1}], "noPartidarios": {"enBlanco": 0, "anulados": 0, "observados": 0}}, {"geoId": "239", "local": "rivera-L079", "ganadorOpcionId": "nacional", "validos": 98, "porOpcion": [{"opcionId": "nacional", "votos": 44}, {"opcionId": "colorado", "votos": 42}, {"opcionId": "frente-amplio", "votos": 12}], "noPartidarios": {"enBlanco": 0, "anulados": 0, "observados": 0}}, {"geoId": "240", "local": "rivera-L080", "ganadorOpcionId": "frente-amplio", "validos": 19, "porOpcion": [{"opcionId": "frente-amplio", "votos": 9}, {"opcionId": "colorado", "votos": 7}, {"opcionId": "nacional", "votos": 3}], "noPartidarios": {"enBlanco": 0, "anulados": 0, "observados": 0}}, {"geoId": "241", "local": "rivera-L081", "ganadorOpcionId": "nacional", "validos": 203, "porOpcion": [{"opcionId": "nacional", "votos": 115}, {"opcionId": "colorado", "votos": 70}, {"opcionId": "frente-amplio", "votos": 18}], "noPartidarios": {"enBlanco": 0, "anulados": 0, "observados": 0}}, {"geoId": "242", "local": "rivera-L081", "ganadorOpcionId": "nacional", "validos": 228, "porOpcion": [{"opcionId": "nacional", "votos": 119}, {"opcionId": "colorado", "votos": 90}, {"opcionId": "frente-amplio", "votos": 19}], "noPartidarios": {"enBlanco": 0, "anulados": 0, "observados": 0}}, {"geoId": "243", "local": "rivera-L081", "ganadorOpcionId": "colorado", "validos": 216, "porOpcion": [{"opcionId": "colorado", "votos": 102}, {"opcionId": "nacional", "votos": 93}, {"opcionId": "frente-amplio", "votos": 21}], "noPartidarios": {"enBlanco": 0, "anulados": 0, "observados": 0}}, {"geoId": "244", "local": "rivera-L081", "ganadorOpcionId": "nacional", "validos": 203, "porOpcion": [{"opcionId": "nacional", "votos": 99}, {"opcionId": "colorado", "votos": 84}, {"opcionId": "frente-amplio", "votos": 20}], "noPartidarios": {"enBlanco": 0, "anulados": 0, "observados": 0}}, {"geoId": "245", "local": "rivera-L082", "ganadorOpcionId": "nacional", "validos": 201, "porOpcion": [{"opcionId": "nacional", "votos": 103}, {"opcionId": "colorado", "votos": 81}, {"opcionId": "frente-amplio", "votos": 17}], "noPartidarios": {"enBlanco": 0, "anulados": 0, "observados": 0}}, {"geoId": "246", "local": "rivera-L082", "ganadorOpcionId": "nacional", "validos": 183, "porOpcion": [{"opcionId": "nacional", "votos": 89}, {"opcionId": "colorado", "votos": 80}, {"opcionId": "frente-amplio", "votos": 14}], "noPartidarios": {"enBlanco": 0, "anulados": 0, "observados": 0}}, {"geoId": "247", "local": "rivera-L082", "ganadorOpcionId": "nacional", "validos": 192, "porOpcion": [{"opcionId": "nacional", "votos": 89}, {"opcionId": "colorado", "votos": 86}, {"opcionId": "frente-amplio", "votos": 17}], "noPartidarios": {"enBlanco": 0, "anulados": 0, "observados": 0}}, {"geoId": "248", "local": "rivera-L082", "ganadorOpcionId": "nacional", "validos": 189, "porOpcion": [{"opcionId": "nacional", "votos": 94}, {"opcionId": "colorado", "votos": 83}, {"opcionId": "frente-amplio", "votos": 12}], "noPartidarios": {"enBlanco": 0, "anulados": 0, "observados": 0}}, {"geoId": "249", "local": "rivera-L082", "ganadorOpcionId": "nacional", "validos": 201, "porOpcion": [{"opcionId": "nacional", "votos": 107}, {"opcionId": "colorado", "votos": 83}, {"opcionId": "frente-amplio", "votos": 11}], "noPartidarios": {"enBlanco": 0, "anulados": 0, "observados": 0}}, {"geoId": "250", "local": "rivera-L083", "ganadorOpcionId": "nacional", "validos": 204, "porOpcion": [{"opcionId": "nacional", "votos": 119}, {"opcionId": "colorado", "votos": 78}, {"opcionId": "frente-amplio", "votos": 7}], "noPartidarios": {"enBlanco": 0, "anulados": 0, "observados": 0}}, {"geoId": "251", "local": "rivera-L083", "ganadorOpcionId": "colorado", "validos": 203, "porOpcion": [{"opcionId": "colorado", "votos": 99}, {"opcionId": "nacional", "votos": 96}, {"opcionId": "frente-amplio", "votos": 8}], "noPartidarios": {"enBlanco": 0, "anulados": 0, "observados": 0}}, {"geoId": "252", "local": "rivera-L084", "ganadorOpcionId": "nacional", "validos": 192, "porOpcion": [{"opcionId": "nacional", "votos": 117}, {"opcionId": "colorado", "votos": 69}, {"opcionId": "frente-amplio", "votos": 6}], "noPartidarios": {"enBlanco": 0, "anulados": 0, "observados": 0}}, {"geoId": "253", "local": "rivera-L085", "ganadorOpcionId": "colorado", "validos": 201, "porOpcion": [{"opcionId": "colorado", "votos": 127}, {"opcionId": "nacional", "votos": 59}, {"opcionId": "frente-amplio", "votos": 15}], "noPartidarios": {"enBlanco": 0, "anulados": 0, "observados": 0}}, {"geoId": "254", "local": "rivera-L086", "ganadorOpcionId": "colorado", "validos": 89, "porOpcion": [{"opcionId": "colorado", "votos": 60}, {"opcionId": "nacional", "votos": 20}, {"opcionId": "frente-amplio", "votos": 9}], "noPartidarios": {"enBlanco": 0, "anulados": 0, "observados": 0}}, {"geoId": "255", "local": "rivera-L086", "ganadorOpcionId": "colorado", "validos": 95, "porOpcion": [{"opcionId": "colorado", "votos": 64}, {"opcionId": "nacional", "votos": 23}, {"opcionId": "frente-amplio", "votos": 8}], "noPartidarios": {"enBlanco": 0, "anulados": 0, "observados": 0}}]}